{"title":"Combined feed","url":"https://MOVIECORD.github.io/daum/all.xml","elements":[{"title":"범죄도시2 (다음영화 영화관 ─ 현재상영)","contents":"22.05.18","link":"https://movie.daum.net/moviedb/main?movieId=122749","retrieved":1651287319549,"image":"https://img1.daumcdn.net/thumb/C408x596/?fname=https%3A%2F%2Ft1.daumcdn.net%2Fmovie%2F3f7e3035989e7918c6426e541c864d0d8a295de2"},{"title":"그대가 조국 (다음영화 영화관 ─ 현재상영)","contents":"22.05.25","link":"https://movie.daum.net/moviedb/main?movieId=159431","retrieved":1653440417489,"image":"https://img1.daumcdn.net/thumb/C408x596/?fname=https%3A%2F%2Ft1.daumcdn.net%2Fmovie%2F700d72335b53bba6e5656ac406c625b58a2b87c9"},{"title":"닥터 스트레인지: 대혼돈의 멀티버스 (다음영화 영화관 ─ 현재상영)","contents":"22.05.04","link":"https://movie.daum.net/moviedb/main?movieId=127221","retrieved":1650453316555,"image":"https://img1.daumcdn.net/thumb/C408x596/?fname=https%3A%2F%2Ft1.daumcdn.net%2Fmovie%2Fa645a5285e0758cc1fdff9b3aa72d5fb234a7fa9"},{"title":"뜨거운 피 (다음영화 영화관 ─ 현재상영)","contents":"22.05.26","link":"https://movie.daum.net/moviedb/main?movieId=125271","retrieved":1653560042752,"image":"https://img1.daumcdn.net/thumb/C408x596/?fname=https%3A%2F%2Ft1.daumcdn.net%2Fmovie%2Fbc40ad380f429b74bc6559c555e43392706bf9c5"},{"title":"피는 물보다 진하다 (다음영화 영화관 ─ 현재상영)","contents":"22.05.25","link":"https://movie.daum.net/moviedb/main?movieId=158844","retrieved":1653440417501,"image":"https://img1.daumcdn.net/thumb/C408x596/?fname=https%3A%2F%2Ft1.daumcdn.net%2Fmovie%2Fed58d7965845aca8b46037cb08ab771432568f7a"},{"title":"안녕하세요 (다음영화 영화관 ─ 현재상영)","contents":"22.05.25","link":"https://movie.daum.net/moviedb/main?movieId=149351","retrieved":1653440417501,"image":"https://img1.daumcdn.net/thumb/C408x596/?fname=https%3A%2F%2Ft1.daumcdn.net%2Fmovie%2F5890a4fa2261b77f06818067b799c1d22bc729cf"},{"title":"오마주 (다음영화 영화관 ─ 현재상영)","contents":"22.05.26","link":"https://movie.daum.net/moviedb/main?movieId=154187","retrieved":1653526942503,"image":"https://img1.daumcdn.net/thumb/C408x596/?fname=https%3A%2F%2Ft1.daumcdn.net%2Fmovie%2Fbeb137937d5cdbe97b3f6bc8d885f8b639d09e64"},{"title":"배드 가이즈 (다음영화 영화관 ─ 현재상영)","contents":"22.05.04","link":"https://movie.daum.net/moviedb/main?movieId=156440","retrieved":1650443099581,"image":"https://img1.daumcdn.net/thumb/C408x596/?fname=https%3A%2F%2Ft1.daumcdn.net%2Fmovie%2F5e205ec697a1386b146b4f8c709f06bcf72c84f4"},{"title":"아치의 노래, 정태춘 (다음영화 영화관 ─ 현재상영)","contents":"22.05.18","link":"https://movie.daum.net/moviedb/main?movieId=152509","retrieved":1651562256210,"image":"https://img1.daumcdn.net/thumb/C408x596/?fname=https%3A%2F%2Ft1.daumcdn.net%2Fmovie%2F9f4fcc696cb967895ae0735c198d0b9f0551fb3a"},{"title":"몬스터 싱어: 매직 인 파리 (다음영화 영화관 ─ 현재상영)","contents":"22.05.26","link":"https://movie.daum.net/moviedb/main?movieId=63792","retrieved":1653526942512,"image":"https://img1.daumcdn.net/thumb/C408x596/?fname=https%3A%2F%2Ft1.daumcdn.net%2Fmovie%2F0cb01acd1813872535e5ba45a8de589ed7ad7d0c"},{"title":"셧 인 (다음영화 영화관 ─ 현재상영)","contents":"22.05.26","link":"https://movie.daum.net/moviedb/main?movieId=156539","retrieved":1653526942509,"image":"https://img1.daumcdn.net/thumb/C408x596/?fname=https%3A%2F%2Ft1.daumcdn.net%2Fmovie%2Fa46680a38861f40be50e6bb711f7ac4c06ea12e4"},{"title":"더 노비스 (다음영화 영화관 ─ 현재상영)","contents":"22.05.25","link":"https://movie.daum.net/moviedb/main?movieId=145810","retrieved":1653440417502,"image":"https://img1.daumcdn.net/thumb/C408x596/?fname=https%3A%2F%2Ft1.daumcdn.net%2Fmovie%2Fc78fb569a394e1eca68145df28165bf61fdc9ee5"},{"title":"극장판 엉덩이 탐정: 수플레 섬의 비밀 (다음영화 영화관 ─ 현재상영)","contents":"22.05.05","link":"https://movie.daum.net/moviedb/main?movieId=153204","retrieved":1653639375287,"image":"https://img1.daumcdn.net/thumb/C408x596/?fname=https%3A%2F%2Ft1.daumcdn.net%2Fmovie%2F8e06f776e191821efe1c0ba65b0222d87d49a5b6"},{"title":"핑크퐁과 아기상어의 월드투어쇼 (다음영화 영화관 ─ 현재상영)","contents":"22.05.28","link":"https://movie.daum.net/moviedb/main?movieId=160617","retrieved":1653520391104},{"title":"나를 만나는 길 (다음영화 영화관 ─ 현재상영)","contents":"22.05.12","link":"https://movie.daum.net/moviedb/main?movieId=114296","retrieved":1651374907219,"image":"https://img1.daumcdn.net/thumb/C408x596/?fname=https%3A%2F%2Ft1.daumcdn.net%2Fmovie%2F864bda5dd54ff661f276e826c749800fd83a7765"},{"title":"우연과 상상 (다음영화 영화관 ─ 현재상영)","contents":"22.05.04","link":"https://movie.daum.net/moviedb/main?movieId=148296","retrieved":1650519388659,"image":"https://img1.daumcdn.net/thumb/C408x596/?fname=https%3A%2F%2Ft1.daumcdn.net%2Fmovie%2F0b2f8065b9484a5be21bf332da7ea64235a755f0"},{"title":"플레이그라운드 (다음영화 영화관 ─ 현재상영)","contents":"22.05.25","link":"https://movie.daum.net/moviedb/main?movieId=152080","retrieved":1653705869717,"image":"https://img1.daumcdn.net/thumb/C408x596/?fname=https%3A%2F%2Ft1.daumcdn.net%2Fmovie%2F8d8808c69a37dac0d97588c6e2b02aaa5518346d"},{"title":"퍼스트 러브 (다음영화 영화관 ─ 현재상영)","contents":"22.05.16","link":"https://movie.daum.net/moviedb/main?movieId=148331","retrieved":1653364238121,"image":"https://img1.daumcdn.net/thumb/C408x596/?fname=https%3A%2F%2Ft1.daumcdn.net%2Fmovie%2Fb17a110cecd283111400ba4326990a4bf487e2fd"},{"title":"매스 (다음영화 영화관 ─ 현재상영)","contents":"22.05.18","link":"https://movie.daum.net/moviedb/main?movieId=147303","retrieved":1653699425615,"image":"https://img1.daumcdn.net/thumb/C408x596/?fname=https%3A%2F%2Ft1.daumcdn.net%2Fmovie%2F26ea483140c84ed654383d90f55f1f71eb36b502"},{"title":"니 부모 얼굴이 보고 싶다 (다음영화 영화관 ─ 현재상영)","contents":"22.04.27","link":"https://movie.daum.net/moviedb/main?movieId=109937","retrieved":1653705869730,"image":"https://img1.daumcdn.net/thumb/C408x596/?fname=https%3A%2F%2Ft1.daumcdn.net%2Fmovie%2F5f1bbf358d905c6a526940b1c81d3196015c3e7b"},{"title":"쥬라기 월드: 도미니언 (다음영화 영화관 ─ 개봉예정)","contents":"22.06.01","link":"https://movie.daum.net/moviedb/main?movieId=139235","retrieved":1653360102099,"image":"https://img1.daumcdn.net/thumb/C408x596/?fname=https%3A%2F%2Ft1.daumcdn.net%2Fmovie%2F5d3c3e6f0e2078681fb0f1a17240e901a8638bd3"},{"title":"극장판 포켓몬스터DP: 기라티나와 하늘의 꽃다발 쉐이미 (다음영화 영화관 ─ 개봉예정)","contents":"22.06.01","link":"https://movie.daum.net/moviedb/main?movieId=47111","retrieved":1653360102114,"image":"https://img1.daumcdn.net/thumb/C408x596/?fname=https%3A%2F%2Ft1.daumcdn.net%2Fmovie%2Fe4b45df35e14a69d7a96579b4c612d2ba25ecd54"},{"title":"브로커 (다음영화 영화관 ─ 개봉예정)","contents":"22.06.08","link":"https://movie.daum.net/moviedb/main?movieId=144096","retrieved":1653360102130,"image":"https://img1.daumcdn.net/thumb/C408x596/?fname=https%3A%2F%2Ft1.daumcdn.net%2Fmovie%2F56e58d88507f1668b65f853e2b8d5ec311f84285"},{"title":"애프터 양 (다음영화 영화관 ─ 개봉예정)","contents":"22.06.01","link":"https://movie.daum.net/moviedb/main?movieId=151102","retrieved":1653360102117,"image":"https://img1.daumcdn.net/thumb/C408x596/?fname=https%3A%2F%2Ft1.daumcdn.net%2Fmovie%2F4ef78f21b43a4d051a178f1ee3f9fbb49cfd930f"},{"title":"카시오페아 (다음영화 영화관 ─ 개봉예정)","contents":"22.06.01","link":"https://movie.daum.net/moviedb/main?movieId=159799","retrieved":1653360102154,"image":"https://img1.daumcdn.net/thumb/C408x596/?fname=https%3A%2F%2Ft1.daumcdn.net%2Fmovie%2F65efe2b2983961db24d721052e3b93300660a1ec"},{"title":"화피사 (다음영화 영화관 ─ 개봉예정)","contents":"22.05","link":"https://movie.daum.net/moviedb/main?movieId=158848","retrieved":1653469993056,"image":"https://img1.daumcdn.net/thumb/C408x596/?fname=https%3A%2F%2Ft1.daumcdn.net%2Fmovie%2F1a505148c50ee3c119f07d0b90b18113488e6a50"},{"title":"그래니트: 트루 솔저 (다음영화 영화관 ─ 개봉예정)","contents":"22.05","link":"https://movie.daum.net/moviedb/main?movieId=159827","retrieved":1653383621367,"image":"https://img1.daumcdn.net/thumb/C408x596/?fname=https%3A%2F%2Ft1.daumcdn.net%2Fmovie%2F84e5baee2cf01b8295d8f2379d4cb437bcb8edc6"},{"title":"셀링 이소벨 (다음영화 영화관 ─ 개봉예정)","contents":"22.06.01","link":"https://movie.daum.net/moviedb/main?movieId=159713","retrieved":1653627001588,"image":"https://img1.daumcdn.net/thumb/C408x596/?fname=https%3A%2F%2Ft1.daumcdn.net%2Fmovie%2F7ae47a6aef2fa420c33faf0ac2f9cc264b1d5419"},{"title":"특수요원 빼꼼 (다음영화 영화관 ─ 개봉예정)","contents":"22.06.01","link":"https://movie.daum.net/moviedb/main?movieId=155632","retrieved":1653542257436,"image":"https://img1.daumcdn.net/thumb/C408x596/?fname=https%3A%2F%2Ft1.daumcdn.net%2Fmovie%2F1a78affe8ba74e86f9fe29d5f2bec620d00a9c8d"},{"title":"괴물, 유령, 자유인 (다음영화 영화관 ─ 개봉예정)","contents":"22.06.02","link":"https://movie.daum.net/moviedb/main?movieId=141710","retrieved":1653473748394,"image":"https://img1.daumcdn.net/thumb/C408x596/?fname=https%3A%2F%2Ft1.daumcdn.net%2Fmovie%2F790154c396e64f40addbcd769e028927d6e5c1c8"},{"title":"올리 마키의 가장 행복한 날 (다음영화 영화관 ─ 개봉예정)","contents":"22.06.02","link":"https://movie.daum.net/moviedb/main?movieId=102922","retrieved":1651731824933,"image":"https://img1.daumcdn.net/thumb/C408x596/?fname=https%3A%2F%2Ft1.daumcdn.net%2Fmovie%2F6fe7ff3173dd268e17894030c2a285773ac24d2e"},{"title":"윤시내가 사라졌다 (다음영화 영화관 ─ 개봉예정)","contents":"22.06.08","link":"https://movie.daum.net/moviedb/main?movieId=146597","retrieved":1652324006467,"image":"https://img1.daumcdn.net/thumb/C408x596/?fname=https%3A%2F%2Ft1.daumcdn.net%2Fmovie%2Ffd174cd7fb84108136744bde6f68b1eba5bd6822"},{"title":"애프터 체르노빌 (다음영화 영화관 ─ 개봉예정)","contents":"22.06.09","link":"https://movie.daum.net/moviedb/main?movieId=157389","retrieved":1653434014587,"image":"https://img1.daumcdn.net/thumb/C408x596/?fname=https%3A%2F%2Ft1.daumcdn.net%2Fmovie%2F97e040403f133b6e6a79272dae83fbbe612f5788"},{"title":"실종 (다음영화 영화관 ─ 개봉예정)","contents":"22.06.15","link":"https://movie.daum.net/moviedb/main?movieId=154171","retrieved":1653452729435,"image":"https://img1.daumcdn.net/thumb/C408x596/?fname=https%3A%2F%2Ft1.daumcdn.net%2Fmovie%2F3f876c14a22b4b8e9f9b81af9a7b68d4781b39bb"},{"title":"경아의 딸 (다음영화 영화관 ─ 개봉예정)","contents":"22.06.16","link":"https://movie.daum.net/moviedb/main?movieId=159312","retrieved":1653646483099,"image":"https://img1.daumcdn.net/thumb/C408x596/?fname=https%3A%2F%2Ft1.daumcdn.net%2Fmovie%2F73a3d766b1ac211970bbac40920d22822d2a0d36"},{"title":"그대라는기억 연숙씨 (다음영화 영화관 ─ 개봉예정)","contents":"22.06.16","link":"https://movie.daum.net/moviedb/main?movieId=159394","retrieved":1653620650142,"image":"https://img1.daumcdn.net/thumb/C408x596/?fname=https%3A%2F%2Ft1.daumcdn.net%2Fmovie%2F8c07a6e8ef7a0a24a0d4e466400b9417ffa7b814"},{"title":"쿵푸 조라: 남편 때려잡기 (다음영화 영화관 ─ 개봉예정)","contents":"22.05.31","link":"https://movie.daum.net/moviedb/main?movieId=157409","retrieved":1653520391105,"image":"https://img1.daumcdn.net/thumb/C408x596/?fname=https%3A%2F%2Ft1.daumcdn.net%2Fmovie%2Fb1079cd3dd0c7d543443777889f03eca5d03c460"},{"title":"허리케인 쓰나미 (다음영화 영화관 ─ 개봉예정)","contents":"22.05","link":"https://movie.daum.net/moviedb/main?movieId=144059","retrieved":1653520391106},{"title":"파라노말 2020 (다음영화 영화관 ─ 개봉예정)","contents":"22.05","link":"https://movie.daum.net/moviedb/main?movieId=144219","retrieved":1653699433491},{"title":"식스 미닛 투 미드나잇 (다음영화 영화관 ─ 개봉예정)","contents":"22.05","link":"https://movie.daum.net/moviedb/main?movieId=148624","retrieved":1653709252047,"image":"https://img1.daumcdn.net/thumb/C408x596/?fname=https%3A%2F%2Ft1.daumcdn.net%2Fmovie%2F5beb4e98a2fbfd76696598173f6c40c8f5f8c4f8"},{"title":"랑군 ([다음영화] 넷플릭스 ─ 종료예정)","contents":"22.05.28","link":"https://movie.daum.net/moviedb/main?movieId=113563","retrieved":1653360110034,"image":"https://img1.daumcdn.net/thumb/C408x596/?fname=http%3A%2F%2Ft1.daumcdn.net%2Fmovie%2F33a40cbb219581209442ca50d1ece1f30c7114b8"},{"title":"더 이퀄라이저 ([다음영화] 넷플릭스 ─ 종료예정)","contents":"22.05.29","link":"https://movie.daum.net/moviedb/main?movieId=78315","retrieved":1653360110045,"image":"https://img1.daumcdn.net/thumb/C408x596/?fname=http%3A%2F%2Ft1.daumcdn.net%2Fcfile%2F233EFA4954BF031C2F"},{"title":"극장판 블리치 지옥편 ([다음영화] 넷플릭스 ─ 종료예정)","contents":"22.05.29","link":"https://movie.daum.net/moviedb/main?movieId=62608","retrieved":1653360110061,"image":"https://img1.daumcdn.net/thumb/C408x596/?fname=http%3A%2F%2Ft1.daumcdn.net%2Fcfile%2F151BEB194CFED86710"},{"title":"극장판 블리치 메모리즈 오브 노바디 ([다음영화] 넷플릭스 ─ 종료예정)","contents":"22.05.29","link":"https://movie.daum.net/moviedb/main?movieId=42820","retrieved":1653360110061,"image":"https://img1.daumcdn.net/thumb/C408x596/?fname=http%3A%2F%2Ft1.daumcdn.net%2Fcfile%2F136F1B10AB14ED4A22"},{"title":"극장판 블리치 페이드 투 블랙 너의 이름을 부른다 ([다음영화] 넷플릭스 ─ 종료예정)","contents":"22.05.29","link":"https://movie.daum.net/moviedb/main?movieId=49174","retrieved":1653360110063,"image":"https://img1.daumcdn.net/thumb/C408x596/?fname=http%3A%2F%2Ft1.daumcdn.net%2Fcfile%2F156C5E10B2484A0975"},{"title":"토탈 리콜 ([다음영화] 넷플릭스 ─ 종료예정)","contents":"22.05.31","link":"https://movie.daum.net/moviedb/main?movieId=59141","retrieved":1651546936047,"image":"https://img1.daumcdn.net/thumb/C408x596/?fname=http%3A%2F%2Ft1.daumcdn.net%2Fcfile%2F190F7C50500630182F"},{"title":"천의 얼굴 프란시스코 ([다음영화] 넷플릭스 ─ 종료예정)","contents":"22.05.31","link":"https://movie.daum.net/moviedb/main?movieId=107062","retrieved":1653535249991,"image":"https://img1.daumcdn.net/thumb/C408x596/?fname=http%3A%2F%2Ft1.daumcdn.net%2Fmovie%2Fcd1c25c8cfcca2c20d59c7e2bf4ec599439301ee"},{"title":"렌즈 ([다음영화] 넷플릭스 ─ 종료예정)","contents":"22.05.31","link":"https://movie.daum.net/moviedb/main?movieId=112788","retrieved":1653360110068,"image":"https://img1.daumcdn.net/thumb/C408x596/?fname=http%3A%2F%2Ft1.daumcdn.net%2Fmovie%2F6786bba1d70ec55a20faa5eee034c5fcac6f4e20"},{"title":"인턴 ([다음영화] 넷플릭스 ─ 종료예정)","contents":"22.05.31","link":"https://movie.daum.net/moviedb/main?movieId=94359","retrieved":1651555225657,"image":"https://img1.daumcdn.net/thumb/C408x596/?fname=http%3A%2F%2Ft1.daumcdn.net%2Fmovie%2F10a0a905726e8d59fc4ab4c4ab0ae9c24a965893"},{"title":"더 라이트 : 악마는 있다 ([다음영화] 넷플릭스 ─ 종료예정)","contents":"22.05.31","link":"https://movie.daum.net/moviedb/main?movieId=63332","retrieved":1651555225657,"image":"https://img1.daumcdn.net/thumb/C408x596/?fname=http%3A%2F%2Ft1.daumcdn.net%2Fcfile%2F191AD8444D8991700B"},{"title":"카멜롯의 전설 ([다음영화] 넷플릭스 ─ 종료예정)","contents":"22.05.31","link":"https://movie.daum.net/moviedb/main?movieId=17098","retrieved":1653360110068,"image":"https://img1.daumcdn.net/thumb/C408x596/?fname=http%3A%2F%2Ft1.daumcdn.net%2Fcfile%2F11227110FEBEDA7715"},{"title":"레고 무비 ([다음영화] 넷플릭스 ─ 종료예정)","contents":"22.05.31","link":"https://movie.daum.net/moviedb/main?movieId=78296","retrieved":1653535250000,"image":"https://img1.daumcdn.net/thumb/C408x596/?fname=http%3A%2F%2Ft1.daumcdn.net%2Fmovie%2F1ff61cf4778deab19a0c5eba45857e0e77023c90"},{"title":"게이샤의 추억 ([다음영화] 넷플릭스 ─ 종료예정)","contents":"22.05.31","link":"https://movie.daum.net/moviedb/main?movieId=40486","retrieved":1651555225680,"image":"https://img1.daumcdn.net/thumb/C408x596/?fname=http%3A%2F%2Ft1.daumcdn.net%2Fcfile%2F17283A4F4DEBE42E1D"},{"title":"택시 드라이버 ([다음영화] 넷플릭스 ─ 종료예정)","contents":"22.05.31","link":"https://movie.daum.net/moviedb/main?movieId=1908","retrieved":1651546936048,"image":"https://img1.daumcdn.net/thumb/C408x596/?fname=http%3A%2F%2Ft1.daumcdn.net%2Fcfile%2F146F1B10AD094A9A40"},{"title":"카우보이 비밥 - 천국의 문 ([다음영화] 넷플릭스 ─ 종료예정)","contents":"22.05.31","link":"https://movie.daum.net/moviedb/main?movieId=32863","retrieved":1653360110073,"image":"https://img1.daumcdn.net/thumb/C408x596/?fname=http%3A%2F%2Ft1.daumcdn.net%2Fcfile%2F12110210A90DBE9ABC"},{"title":"노인을 위한 나라는 없다 ([다음영화] 넷플릭스 ─ 종료예정)","contents":"22.05.31","link":"https://movie.daum.net/moviedb/main?movieId=43584","retrieved":1651555225686,"image":"https://img1.daumcdn.net/thumb/C408x596/?fname=http%3A%2F%2Ft1.daumcdn.net%2Fmovie%2F1ae9135165d7f0955058bca1d01ee512b273e238"},{"title":"퀸카로 살아남는 법 ([다음영화] 넷플릭스 ─ 종료예정)","contents":"22.05.31","link":"https://movie.daum.net/moviedb/main?movieId=39506","retrieved":1651555225688,"image":"https://img1.daumcdn.net/thumb/C408x596/?fname=http%3A%2F%2Ft1.daumcdn.net%2Fcfile%2F14110210A907373554"},{"title":"마더! ([다음영화] 넷플릭스 ─ 종료예정)","contents":"22.05.31","link":"https://movie.daum.net/moviedb/main?movieId=112234","retrieved":1651555225691,"image":"https://img1.daumcdn.net/thumb/C408x596/?fname=http%3A%2F%2Ft1.daumcdn.net%2Fmovie%2F7f04b2524db42230ad528fc49088f0197d309227"},{"title":"공각기동대 : 고스트 인 더 쉘 ([다음영화] 넷플릭스 ─ 종료예정)","contents":"22.05.31","link":"https://movie.daum.net/moviedb/main?movieId=91349","retrieved":1651555225693,"image":"https://img1.daumcdn.net/thumb/C408x596/?fname=http%3A%2F%2Ft1.daumcdn.net%2Fmovie%2Fa58ed2c8af22279f4c834b9735e8139d297a72e1"},{"title":"애프터 어스 ([다음영화] 넷플릭스 ─ 종료예정)","contents":"22.05.31","link":"https://movie.daum.net/moviedb/main?movieId=68667","retrieved":1653360110097,"image":"https://img1.daumcdn.net/thumb/C408x596/?fname=http%3A%2F%2Ft1.daumcdn.net%2Fcfile%2F224CDC4C51A455382E"},{"title":"굿 럭 척 ([다음영화] 넷플릭스 ─ 종료예정)","contents":"22.05.31","link":"https://movie.daum.net/moviedb/main?movieId=43718","retrieved":1653535250015,"image":"https://img1.daumcdn.net/thumb/C408x596/?fname=http%3A%2F%2Ft1.daumcdn.net%2Fcfile%2F136F1B10AC4FAAFDB0"},{"title":"써스펙트 ([다음영화] 넷플릭스 ─ 종료예정)","contents":"22.05.31","link":"https://movie.daum.net/moviedb/main?movieId=31262","retrieved":1651555225696,"image":"https://img1.daumcdn.net/thumb/C408x596/?fname=http%3A%2F%2Ft1.daumcdn.net%2Fcfile%2F144EA7314D020D6550"},{"title":"컨뎀드 ([다음영화] 넷플릭스 ─ 종료예정)","contents":"22.05.31","link":"https://movie.daum.net/moviedb/main?movieId=43086","retrieved":1653360110103,"image":"https://img1.daumcdn.net/thumb/C408x596/?fname=http%3A%2F%2Ft1.daumcdn.net%2Fcfile%2F146F1B10ABEF0F710C"},{"title":"뜻밖의 룸메이트 ([다음영화] 넷플릭스 ─ 종료예정)","contents":"22.05.31","link":"https://movie.daum.net/moviedb/main?movieId=115886","retrieved":1651555225698,"image":"https://img1.daumcdn.net/thumb/C408x596/?fname=http%3A%2F%2Ft1.daumcdn.net%2Fmovie%2F3d2154d135253594f5b072e92f9cf534e80735b8"},{"title":"파프리카 ([다음영화] 넷플릭스 ─ 종료예정)","contents":"22.05.31","link":"https://movie.daum.net/moviedb/main?movieId=42497","retrieved":1651555225700,"image":"https://img1.daumcdn.net/thumb/C408x596/?fname=http%3A%2F%2Ft1.daumcdn.net%2Fcfile%2F116F1B10AC63D9B6DE"},{"title":"인사이드 잡 ([다음영화] 넷플릭스 ─ 종료예정)","contents":"22.05.31","link":"https://movie.daum.net/moviedb/main?movieId=57006","retrieved":1653360110104,"image":"https://img1.daumcdn.net/thumb/C408x596/?fname=http%3A%2F%2Ft1.daumcdn.net%2Fcfile%2F1775D93F4DAF64AE01"},{"title":"수어사이드 스쿼드 ([다음영화] 넷플릭스 ─ 종료예정)","contents":"22.06.02","link":"https://movie.daum.net/moviedb/main?movieId=90177","retrieved":1653360110108,"image":"https://img1.daumcdn.net/thumb/C408x596/?fname=http%3A%2F%2Ft1.daumcdn.net%2Fmovie%2Fca76922561a547ed64982152f4880918662faa78"},{"title":"수퍼 소닉 ([다음영화] 넷플릭스 ─ 종료예정)","contents":"22.06.04","link":"https://movie.daum.net/moviedb/main?movieId=127118","retrieved":1653360110111,"image":"https://img1.daumcdn.net/thumb/C408x596/?fname=http%3A%2F%2Ft1.daumcdn.net%2Fmovie%2Ff50d6fca70054f3fa7e991443b3795891578899401302"},{"title":"언프리티 소셜 스타 ([다음영화] 넷플릭스 ─ 종료예정)","contents":"22.06.06","link":"https://movie.daum.net/moviedb/main?movieId=108967","retrieved":1653360110119,"image":"https://img1.daumcdn.net/thumb/C408x596/?fname=http%3A%2F%2Ft1.daumcdn.net%2Fmovie%2Fa633395d37650d45144e6c0badc07b81ed1491e7"},{"title":"보블헤드 - 더 무비 ([다음영화] 넷플릭스 ─ 종료예정)","contents":"22.06.07","link":"https://movie.daum.net/moviedb/main?movieId=151156","retrieved":1653360110121,"image":"https://img1.daumcdn.net/thumb/C408x596/?fname=https%3A%2F%2Ft1.daumcdn.net%2Fmovie%2Fd71deda861df8ab9afe32b0b37fe7a05ec767756"},{"title":"그것 ([다음영화] 넷플릭스 ─ 종료예정)","contents":"22.06.15","link":"https://movie.daum.net/moviedb/main?movieId=104727","retrieved":1653360110121,"image":"https://img1.daumcdn.net/thumb/C408x596/?fname=http%3A%2F%2Ft1.daumcdn.net%2Fmovie%2Fad3538bc96b52ab82c91e15684fb292b2bb9c2bd"},{"title":"히든 페이스 ([다음영화] 넷플릭스 ─ 종료예정)","contents":"22.06.17","link":"https://movie.daum.net/moviedb/main?movieId=72730","retrieved":1653360110122,"image":"https://img1.daumcdn.net/thumb/C408x596/?fname=http%3A%2F%2Ft1.daumcdn.net%2Fcfile%2F2654614E540685EA05"},{"title":"라스트 나잇 인 소호 ([다음영화] 넷플릭스 ─ 공개예정)","contents":"22.05.29","link":"https://movie.daum.net/moviedb/main?movieId=129679","retrieved":1653369533313,"image":"https://img1.daumcdn.net/thumb/C408x596/?fname=https%3A%2F%2Ft1.daumcdn.net%2Fmovie%2Fa3d67cc5d4db5a5a0ae7495e64178588c7929390"},{"title":"쉘부르의 우산 ([다음영화] 넷플릭스 ─ 공개예정)","contents":"22.05.30","link":"https://movie.daum.net/moviedb/main?movieId=10323","retrieved":1653639396362,"image":"https://img1.daumcdn.net/thumb/C408x596/?fname=http%3A%2F%2Ft1.daumcdn.net%2Fmovie%2Fcc385b400d3f4f6ea967da15a4e074701564118960663"},{"title":"카드카운터 ([다음영화] 넷플릭스 ─ 공개예정)","contents":"22.05.30","link":"https://movie.daum.net/moviedb/main?movieId=152813","retrieved":1653360118163,"image":"https://img1.daumcdn.net/thumb/C408x596/?fname=https%3A%2F%2Ft1.daumcdn.net%2Fmovie%2F491291870a24063c171c8b062a1c74f91bc98efe"},{"title":"아무도 없는 곳 ([다음영화] 넷플릭스 ─ 공개예정)","contents":"22.06.01","link":"https://movie.daum.net/moviedb/main?movieId=129990","retrieved":1653360118166,"image":"https://img1.daumcdn.net/thumb/C408x596/?fname=https%3A%2F%2Ft1.daumcdn.net%2Fmovie%2F845a3ab98e57c285df70bd910248d7559084b9f6"},{"title":"영웅 : 천하의 시작 ([다음영화] 넷플릭스 ─ 공개예정)","contents":"22.06.01","link":"https://movie.daum.net/moviedb/main?movieId=4142","retrieved":1653360118170,"image":"https://img1.daumcdn.net/thumb/C408x596/?fname=http%3A%2F%2Ft1.daumcdn.net%2Fmovie%2Fd6a62a9d41e44dbe9ea711bb32c69da51553654062841"},{"title":"라스베가스를 떠나며 ([다음영화] 넷플릭스 ─ 공개예정)","contents":"22.06.01","link":"https://movie.daum.net/moviedb/main?movieId=1860","retrieved":1653360118173,"image":"https://img1.daumcdn.net/thumb/C408x596/?fname=http%3A%2F%2Ft1.daumcdn.net%2Fcfile%2F146F1B10ACCD3D10D3"},{"title":"아이언 자이언트 ([다음영화] 넷플릭스 ─ 공개예정)","contents":"22.06.01","link":"https://movie.daum.net/moviedb/main?movieId=1913","retrieved":1653360118173,"image":"https://img1.daumcdn.net/thumb/C408x596/?fname=http%3A%2F%2Ft1.daumcdn.net%2Fmovie%2Ffcc84495f0204c0d98b7c397e630c99e1568619556120"},{"title":"리포 맨 ([다음영화] 넷플릭스 ─ 공개예정)","contents":"22.06.01","link":"https://movie.daum.net/moviedb/main?movieId=55344","retrieved":1653360118177,"image":"https://img1.daumcdn.net/thumb/C408x596/?fname=http%3A%2F%2Ft1.daumcdn.net%2Fmovie%2F0c43447a8567ddae37fe181eab1f0548f8b9cd1a"},{"title":"타이탄족의 멸망 ([다음영화] 넷플릭스 ─ 공개예정)","contents":"22.06.01","link":"https://movie.daum.net/moviedb/main?movieId=20358","retrieved":1653360118181,"image":"https://img1.daumcdn.net/thumb/C408x596/?fname=http%3A%2F%2Ft1.daumcdn.net%2Fcfile%2F134D4110B2558E81D1"},{"title":"랜섬 ([다음영화] 넷플릭스 ─ 공개예정)","contents":"22.06.01","link":"https://movie.daum.net/moviedb/main?movieId=1807","retrieved":1653360118181,"image":"https://img1.daumcdn.net/thumb/C408x596/?fname=http%3A%2F%2Ft1.daumcdn.net%2Fcfile%2F1340FB10AB82617F80"},{"title":"나이트폴 ([다음영화] 넷플릭스 ─ 공개예정)","contents":"22.06.01","link":"https://movie.daum.net/moviedb/main?movieId=70603","retrieved":1653360118182,"image":"https://img1.daumcdn.net/thumb/C408x596/?fname=http%3A%2F%2Ft1.daumcdn.net%2Fcfile%2F19520B50503AFCB32E"},{"title":"모범시민 ([다음영화] 넷플릭스 ─ 공개예정)","contents":"22.06.01","link":"https://movie.daum.net/moviedb/main?movieId=53416","retrieved":1653369533323,"image":"https://img1.daumcdn.net/thumb/C408x596/?fname=http%3A%2F%2Ft1.daumcdn.net%2Fcfile%2F1677DF274AE4E80665"},{"title":"나를 책임져, 알피 ([다음영화] 넷플릭스 ─ 공개예정)","contents":"22.06.01","link":"https://movie.daum.net/moviedb/main?movieId=39247","retrieved":1653369533326,"image":"https://img1.daumcdn.net/thumb/C408x596/?fname=http%3A%2F%2Ft1.daumcdn.net%2Fcfile%2F11110210A907A6EEAA"},{"title":"램페이지 ([다음영화] 넷플릭스 ─ 공개예정)","contents":"22.06.01","link":"https://movie.daum.net/moviedb/main?movieId=108275","retrieved":1653639396392,"image":"https://img1.daumcdn.net/thumb/C408x596/?fname=http%3A%2F%2Ft1.daumcdn.net%2Fmovie%2F4e64c9bfb9116735f0b69cd0fd289e104ad06542"},{"title":"저스티스 리그 ([다음영화] 넷플릭스 ─ 공개예정)","contents":"22.06.01","link":"https://movie.daum.net/moviedb/main?movieId=102145","retrieved":1653639396399,"image":"https://img1.daumcdn.net/thumb/C408x596/?fname=http%3A%2F%2Ft1.daumcdn.net%2Fmovie%2Fe45247056330808df432dcbdc8757d920a3b0938"},{"title":"메가로돈 ([다음영화] 넷플릭스 ─ 공개예정)","contents":"22.06.01","link":"https://movie.daum.net/moviedb/main?movieId=118342","retrieved":1653639396399,"image":"https://img1.daumcdn.net/thumb/C408x596/?fname=http%3A%2F%2Ft1.daumcdn.net%2Fmovie%2Ff8573ba084988d5b39080eeeeeaeaa434159104f"},{"title":"오션스8 ([다음영화] 넷플릭스 ─ 공개예정)","contents":"22.06.01","link":"https://movie.daum.net/moviedb/main?movieId=108442","retrieved":1653639396399,"image":"https://img1.daumcdn.net/thumb/C408x596/?fname=http%3A%2F%2Ft1.daumcdn.net%2Fmovie%2Faf057650e699d070cbf3f59daefd565cf13bf210"},{"title":"레디 플레이어 원 ([다음영화] 넷플릭스 ─ 공개예정)","contents":"22.06.01","link":"https://movie.daum.net/moviedb/main?movieId=96030","retrieved":1653639396400,"image":"https://img1.daumcdn.net/thumb/C408x596/?fname=http%3A%2F%2Ft1.daumcdn.net%2Fmovie%2Fc8fc63415f6a93f6c8606b22b2a3c63c5e4e3f3c"},{"title":"게임나이트 ([다음영화] 넷플릭스 ─ 공개예정)","contents":"22.06.01","link":"https://movie.daum.net/moviedb/main?movieId=116754","retrieved":1653639396402,"image":"https://img1.daumcdn.net/thumb/C408x596/?fname=http%3A%2F%2Ft1.daumcdn.net%2Fmovie%2Fbb7a4d3ad123ec47f0556cbd31eb8fe7a3b4297b"},{"title":"15시 17분 파리행 열차 ([다음영화] 넷플릭스 ─ 공개예정)","contents":"22.06.01","link":"https://movie.daum.net/moviedb/main?movieId=114899","retrieved":1653639396405,"image":"https://img1.daumcdn.net/thumb/C408x596/?fname=http%3A%2F%2Ft1.daumcdn.net%2Fmovie%2Fb59e50ed943209ba328bea2fd305cd3aa309568b"},{"title":"허슬 ([다음영화] 넷플릭스 ─ 공개예정)","contents":"22.06.08","link":"https://movie.daum.net/moviedb/main?movieId=160239","retrieved":1653360118184,"image":"https://img1.daumcdn.net/thumb/C408x596/?fname=https%3A%2F%2Ft1.daumcdn.net%2Fmovie%2F2b9069595b0b43b12f6d0093a1f12dcd40630351"},{"title":"트리 오브 피스 ([다음영화] 넷플릭스 ─ 공개예정)","contents":"22.06.10","link":"https://movie.daum.net/moviedb/main?movieId=149241","retrieved":1653360118188,"image":"https://img1.daumcdn.net/thumb/C408x596/?fname=https%3A%2F%2Ft1.daumcdn.net%2Fmovie%2Fb2740076d2b630a99d25316e11850023e834e142"},{"title":"제니퍼 로페즈: 내 인생의 하프타임 ([다음영화] 넷플릭스 ─ 공개예정)","contents":"22.06.14","link":"https://movie.daum.net/moviedb/main?movieId=159441","retrieved":1653369533334,"image":"https://img1.daumcdn.net/thumb/C408x596/?fname=https%3A%2F%2Ft1.daumcdn.net%2Fmovie%2Fbbfde329b1a199bb7b24f8097e186f9d6fc3922b"},{"title":"켄타우로스 ([다음영화] 넷플릭스 ─ 공개예정)","contents":"22.06.15","link":"https://movie.daum.net/moviedb/main?movieId=160314","retrieved":1653360118189,"image":"https://img1.daumcdn.net/thumb/C408x596/?fname=https%3A%2F%2Ft1.daumcdn.net%2Fmovie%2Fe918d0ed6e6199afbefbe536e02410a31110a2c3"},{"title":"불도저에 탄 소녀 ([다음영화] 넷플릭스 ─ 공개예정)","contents":"22.06.15","link":"https://movie.daum.net/moviedb/main?movieId=153127","retrieved":1653535258269,"image":"https://img1.daumcdn.net/thumb/C408x596/?fname=https%3A%2F%2Ft1.daumcdn.net%2Fmovie%2Fcf40ac21c4b32fa6aa18c5048e0495e9b70ef63c"},{"title":"컬리전 ([다음영화] 넷플릭스 ─ 공개예정)","contents":"22.06.16","link":"https://movie.daum.net/moviedb/main?movieId=159788","retrieved":1653369533338,"image":"https://img1.daumcdn.net/thumb/C408x596/?fname=https%3A%2F%2Ft1.daumcdn.net%2Fmovie%2F7727f71b8627e70c2438af25c90d29825c34332e"},{"title":"스파이더헤드 ([다음영화] 넷플릭스 ─ 공개예정)","contents":"22.06.17","link":"https://movie.daum.net/moviedb/main?movieId=158046","retrieved":1653360118192,"image":"https://img1.daumcdn.net/thumb/C408x596/?fname=https%3A%2F%2Ft1.daumcdn.net%2Fmovie%2Fda07992797dad9c03addeca502cda626d679aa20"},{"title":"컬러풀 웨딩즈 ([다음영화] 왓챠 ─ 종료예정)","contents":"22.05.28","link":"https://movie.daum.net/moviedb/main?movieId=85615","retrieved":1653360126008,"image":"https://img1.daumcdn.net/thumb/C408x596/?fname=http%3A%2F%2Ft1.daumcdn.net%2Fcfile%2F214FE0475423F8BE17"},{"title":"파리지엔느 프로젝트 ([다음영화] 왓챠 ─ 종료예정)","contents":"22.05.28","link":"https://movie.daum.net/moviedb/main?movieId=80678","retrieved":1653360126008,"image":"https://img1.daumcdn.net/thumb/C408x596/?fname=http%3A%2F%2Ft1.daumcdn.net%2Fmovie%2F3ca4ee1e7725d9c2f928371af797e75b2fc11013"},{"title":"할리우드의 악몽 ([다음영화] 왓챠 ─ 종료예정)","contents":"22.05.31","link":"https://movie.daum.net/moviedb/main?movieId=143200","retrieved":1653360126009,"image":"https://img1.daumcdn.net/thumb/C408x596/?fname=https%3A%2F%2Ft1.daumcdn.net%2Fmovie%2Fdc02c886af2df722fece470bd5ebff99f7687643"},{"title":"시간위의 집 ([다음영화] 왓챠 ─ 종료예정)","contents":"22.05.31","link":"https://movie.daum.net/moviedb/main?movieId=105590","retrieved":1653360126009,"image":"https://img1.daumcdn.net/thumb/C408x596/?fname=http%3A%2F%2Ft1.daumcdn.net%2Fmovie%2F380abcba4350f7d7bc3068d9b1b39250637b998b"},{"title":"소드 마스터: 절대 강호의 죽음 ([다음영화] 왓챠 ─ 종료예정)","contents":"22.05.31","link":"https://movie.daum.net/moviedb/main?movieId=107431","retrieved":1653360126009,"image":"https://img1.daumcdn.net/thumb/C408x596/?fname=http%3A%2F%2Ft1.daumcdn.net%2Fmovie%2F0f179253a7dad17fa78176a45dffba6aef575d16"},{"title":"타임 어게인 ([다음영화] 왓챠 ─ 종료예정)","contents":"22.05.31","link":"https://movie.daum.net/moviedb/main?movieId=143199","retrieved":1653360126012,"image":"https://img1.daumcdn.net/thumb/C408x596/?fname=https%3A%2F%2Ft1.daumcdn.net%2Fmovie%2F977c53df61783b797df87e75e275e7ae3cefc702"},{"title":"월터 교수의 마지막 강의 ([다음영화] 왓챠 ─ 종료예정)","contents":"22.05.31","link":"https://movie.daum.net/moviedb/main?movieId=96422","retrieved":1653360126012,"image":"https://img1.daumcdn.net/thumb/C408x596/?fname=http%3A%2F%2Ft1.daumcdn.net%2Fmovie%2F9e759a6b1db1c26f995e4c563edb298c3a6bfc17"},{"title":"빈센트 ([다음영화] 왓챠 ─ 종료예정)","contents":"22.05.31","link":"https://movie.daum.net/moviedb/main?movieId=88933","retrieved":1653360126021,"image":"https://img1.daumcdn.net/thumb/C408x596/?fname=http%3A%2F%2Ft1.daumcdn.net%2Fmovie%2Fe3332e6d0c2d1e25517813844b54623916ec6340"},{"title":"죽음의 천사 ([다음영화] 왓챠 ─ 종료예정)","contents":"22.05.31","link":"https://movie.daum.net/moviedb/main?movieId=84470","retrieved":1653360126021,"image":"https://img1.daumcdn.net/thumb/C408x596/?fname=http%3A%2F%2Ft1.daumcdn.net%2Fcfile%2F276A254C5374445106"},{"title":"코만도 ([다음영화] 왓챠 ─ 종료예정)","contents":"22.05.31","link":"https://movie.daum.net/moviedb/main?movieId=143198","retrieved":1653360126021,"image":"https://img1.daumcdn.net/thumb/C408x596/?fname=https%3A%2F%2Ft1.daumcdn.net%2Fmovie%2F89f0858e9b6ad0b9e038805d5ba13ee190b20001"},{"title":"핼러윈 밤의 생명체들 ([다음영화] 왓챠 ─ 종료예정)","contents":"22.05.31","link":"https://movie.daum.net/moviedb/main?movieId=143201","retrieved":1653360126025,"image":"https://img1.daumcdn.net/thumb/C408x596/?fname=https%3A%2F%2Ft1.daumcdn.net%2Fmovie%2F565df3c88e541d15daf0c8072a4bfc8009510788"},{"title":"아마도 내일은 ([다음영화] 왓챠 ─ 종료예정)","contents":"22.05.31","link":"https://movie.daum.net/moviedb/main?movieId=108338","retrieved":1653360126026,"image":"https://img1.daumcdn.net/thumb/C408x596/?fname=http%3A%2F%2Ft1.daumcdn.net%2Fmovie%2F516303bc4f20692d89721a135bbfc3ce9d1d8354"},{"title":"오스트레일리언즈 ([다음영화] 왓챠 ─ 종료예정)","contents":"22.05.31","link":"https://movie.daum.net/moviedb/main?movieId=143197","retrieved":1653360126026,"image":"https://img1.daumcdn.net/thumb/C408x596/?fname=https%3A%2F%2Ft1.daumcdn.net%2Fmovie%2F0ebe7bf6247d410314eaeb8888cc58237d54c392"},{"title":"투 마더스 ([다음영화] 왓챠 ─ 종료예정)","contents":"22.06.03","link":"https://movie.daum.net/moviedb/main?movieId=76587","retrieved":1653360126026,"image":"https://img1.daumcdn.net/thumb/C408x596/?fname=http%3A%2F%2Ft1.daumcdn.net%2Fcfile%2F220F304E51E79BBA19"},{"title":"천하무적 키코리키 ([다음영화] 왓챠 ─ 종료예정)","contents":"22.06.03","link":"https://movie.daum.net/moviedb/main?movieId=86884","retrieved":1653360126031,"image":"https://img1.daumcdn.net/thumb/C408x596/?fname=http%3A%2F%2Ft1.daumcdn.net%2Fcfile%2F25431B5053AA8C852A"},{"title":"파라다이스 ([다음영화] 왓챠 ─ 종료예정)","contents":"22.06.04","link":"https://movie.daum.net/moviedb/main?movieId=78120","retrieved":1653360126031,"image":"https://img1.daumcdn.net/thumb/C408x596/?fname=http%3A%2F%2Ft1.daumcdn.net%2Fcfile%2F2516474D53745AAA26"},{"title":"마데아 : 증인보호프로그램 ([다음영화] 왓챠 ─ 종료예정)","contents":"22.06.04","link":"https://movie.daum.net/moviedb/main?movieId=71600","retrieved":1653360126034,"image":"https://img1.daumcdn.net/thumb/C408x596/?fname=http%3A%2F%2Ft1.daumcdn.net%2Fcfile%2F23130949517DC5412F"},{"title":"에벌리 ([다음영화] 왓챠 ─ 종료예정)","contents":"22.06.06","link":"https://movie.daum.net/moviedb/main?movieId=90195","retrieved":1653360126034,"image":"https://img1.daumcdn.net/thumb/C408x596/?fname=http%3A%2F%2Ft1.daumcdn.net%2Fmovie%2F2d8880dfcb2a73c3a17dcdbf8385f1e96bfd07fd"},{"title":"라비앙 로즈 ([다음영화] 왓챠 ─ 종료예정)","contents":"22.06.07","link":"https://movie.daum.net/moviedb/main?movieId=43049","retrieved":1653369540324,"image":"https://img1.daumcdn.net/thumb/C408x596/?fname=http%3A%2F%2Ft1.daumcdn.net%2Fcfile%2F116F1B10AC681E1B12"},{"title":"쉘로우 그레이브 ([다음영화] 왓챠 ─ 종료예정)","contents":"22.06.08","link":"https://movie.daum.net/moviedb/main?movieId=2058","retrieved":1653455886615,"image":"https://img1.daumcdn.net/thumb/C408x596/?fname=http%3A%2F%2Ft1.daumcdn.net%2Fmovie%2Fad3437d193720591a89abc5e65cf08c2fcd0b2dc"},{"title":"미스터 주: 사라진 VIP ([다음영화] 왓챠 ─ 종료예정)","contents":"22.06.08","link":"https://movie.daum.net/moviedb/main?movieId=121369","retrieved":1653535266731,"image":"https://img1.daumcdn.net/thumb/C408x596/?fname=http%3A%2F%2Ft1.daumcdn.net%2Fmovie%2F62a1145c988a419bb88ccebbc1e4c38e1579678173231"},{"title":"이터너티 ([다음영화] 카카오페이지 ─ 종료예정)","contents":"22.05.29","link":"https://movie.daum.net/moviedb/main?movieId=107261","retrieved":1653360140119,"image":"https://img1.daumcdn.net/thumb/C408x596/?fname=http%3A%2F%2Ft1.daumcdn.net%2Fmovie%2F27349022a2e1a06335f19ab2b9c958fbc3933578"},{"title":"존 윅 ([다음영화] 카카오페이지 ─ 종료예정)","contents":"22.05.30","link":"https://movie.daum.net/moviedb/main?movieId=88256","retrieved":1653360140122,"image":"https://img1.daumcdn.net/thumb/C408x596/?fname=https%3A%2F%2Ft1.daumcdn.net%2Fmovie%2F93ca802a289d7fc8ef530e016669d95b56b13b7c"},{"title":"특별시민 ([다음영화] 카카오페이지 ─ 종료예정)","contents":"22.05.30","link":"https://movie.daum.net/moviedb/main?movieId=101076","retrieved":1653360140135,"image":"https://img1.daumcdn.net/thumb/C408x596/?fname=http%3A%2F%2Ft1.daumcdn.net%2Fmovie%2F9b9b7250142478c8ae337803344a8fe0fbc3aa20"},{"title":"내 아내와 결혼해 주세요 ([다음영화] 카카오페이지 ─ 종료예정)","contents":"22.05.30","link":"https://movie.daum.net/moviedb/main?movieId=107644","retrieved":1653360140136,"image":"https://img1.daumcdn.net/thumb/C408x596/?fname=http%3A%2F%2Ft1.daumcdn.net%2Fmovie%2F1453abd3b2f2fb7b0f0e594777d9a1d5d9ce2f63"},{"title":"투 마더스 ([다음영화] 카카오페이지 ─ 종료예정)","contents":"22.05.31","link":"https://movie.daum.net/moviedb/main?movieId=76587","retrieved":1653360126026,"image":"https://img1.daumcdn.net/thumb/C408x596/?fname=http%3A%2F%2Ft1.daumcdn.net%2Fcfile%2F220F304E51E79BBA19"},{"title":"카페, 한 사람을 기다리다 ([다음영화] 카카오페이지 ─ 종료예정)","contents":"22.05.31","link":"https://movie.daum.net/moviedb/main?movieId=87970","retrieved":1653360140138,"image":"https://img1.daumcdn.net/thumb/C408x596/?fname=http%3A%2F%2Ft1.daumcdn.net%2Fmovie%2F92e52d83b91125c056f8e10cc3a348ee6c4f740a"},{"title":"콜트 45 ([다음영화] 카카오페이지 ─ 종료예정)","contents":"22.05.31","link":"https://movie.daum.net/moviedb/main?movieId=88002","retrieved":1653360140139,"image":"https://img1.daumcdn.net/thumb/C408x596/?fname=https%3A%2F%2Ft1.daumcdn.net%2Fmovie%2Fa06711df7c670e33ae7c33b0458a2edebac576d5"},{"title":"굿 파이터 ([다음영화] 카카오페이지 ─ 종료예정)","contents":"22.05.31","link":"https://movie.daum.net/moviedb/main?movieId=92903","retrieved":1653360140140,"image":"https://img1.daumcdn.net/thumb/C408x596/?fname=http%3A%2F%2Ft1.daumcdn.net%2Fmovie%2Fee2ad56c293c03928191573d8106dfef62f19a45"},{"title":"시간위의 집 ([다음영화] 카카오페이지 ─ 종료예정)","contents":"22.05.31","link":"https://movie.daum.net/moviedb/main?movieId=105590","retrieved":1653360126009,"image":"https://img1.daumcdn.net/thumb/C408x596/?fname=http%3A%2F%2Ft1.daumcdn.net%2Fmovie%2F380abcba4350f7d7bc3068d9b1b39250637b998b"},{"title":"전설의 검 ([다음영화] 카카오페이지 ─ 종료예정)","contents":"22.05.31","link":"https://movie.daum.net/moviedb/main?movieId=108288","retrieved":1653360140147,"image":"https://img1.daumcdn.net/thumb/C408x596/?fname=http%3A%2F%2Ft1.daumcdn.net%2Fmovie%2F0999f6d9f6ad8ecf1e1bb9ea68591ce44092f6d6"},{"title":"절대 무림 신공 ([다음영화] 카카오페이지 ─ 종료예정)","contents":"22.05.31","link":"https://movie.daum.net/moviedb/main?movieId=111780","retrieved":1653360140149,"image":"https://img1.daumcdn.net/thumb/C408x596/?fname=http%3A%2F%2Ft1.daumcdn.net%2Fmovie%2F3028b7feb4267716e842dba5c0d0d96007c13a54"},{"title":"애로우헤드 ([다음영화] 카카오페이지 ─ 종료예정)","contents":"22.05.31","link":"https://movie.daum.net/moviedb/main?movieId=111847","retrieved":1653360140152,"image":"https://img1.daumcdn.net/thumb/C408x596/?fname=http%3A%2F%2Ft1.daumcdn.net%2Fmovie%2F23a5b6616b8e3c164e583123edf9660952f6d8e8"},{"title":"호텔 룸 ([다음영화] 카카오페이지 ─ 종료예정)","contents":"22.06.04","link":"https://movie.daum.net/moviedb/main?movieId=88763","retrieved":1653360140152,"image":"https://img1.daumcdn.net/thumb/C408x596/?fname=http%3A%2F%2Ft1.daumcdn.net%2Fmovie%2F182df339e963eaff000278e74ba5621e1e9b7bb0"},{"title":"디스트럭션 베이비 ([다음영화] 카카오페이지 ─ 종료예정)","contents":"22.06.07","link":"https://movie.daum.net/moviedb/main?movieId=105013","retrieved":1653360140153,"image":"https://img1.daumcdn.net/thumb/C408x596/?fname=http%3A%2F%2Ft1.daumcdn.net%2Fmovie%2Fa01fcb347d035dc0f245e22a7eed7409f5667d8a"},{"title":"천하영웅 소림명탐 ([다음영화] 카카오페이지 ─ 종료예정)","contents":"22.06.07","link":"https://movie.daum.net/moviedb/main?movieId=111778","retrieved":1653360140153,"image":"https://img1.daumcdn.net/thumb/C408x596/?fname=http%3A%2F%2Ft1.daumcdn.net%2Fmovie%2Fb46cf0c3fc919ab1e3707bab66e0aeaf79da6a54"},{"title":"필로우 북 ([다음영화] 카카오페이지 ─ 종료예정)","contents":"22.06.08","link":"https://movie.daum.net/moviedb/main?movieId=2307","retrieved":1653360140165,"image":"https://img1.daumcdn.net/thumb/C408x596/?fname=http%3A%2F%2Ft1.daumcdn.net%2Fmovie%2Fa0ba5d0a81cb26304570df470d77ffa600c720eb"},{"title":"계춘할망 ([다음영화] 카카오페이지 ─ 종료예정)","contents":"22.06.09","link":"https://movie.daum.net/moviedb/main?movieId=91615","retrieved":1653409629225,"image":"https://img1.daumcdn.net/thumb/C408x596/?fname=http%3A%2F%2Ft1.daumcdn.net%2Fmovie%2F6e04ebeeca97cd4baccf41143c54e04d8897e5c2"},{"title":"인베이젼 2020 ([다음영화] 카카오페이지 ─ 종료예정)","contents":"22.06.09","link":"https://movie.daum.net/moviedb/main?movieId=140920","retrieved":1653466639359,"image":"https://img1.daumcdn.net/thumb/C408x596/?fname=https%3A%2F%2Ft1.daumcdn.net%2Fmovie%2F0533fa669d8366241b52dee9aff1d7a10ec22513"},{"title":"족구왕 ([다음영화] 카카오페이지 ─ 종료예정)","contents":"22.06.10","link":"https://movie.daum.net/moviedb/main?movieId=81599","retrieved":1653495517352,"image":"https://img1.daumcdn.net/thumb/C408x596/?fname=http%3A%2F%2Ft1.daumcdn.net%2Fcfile%2F260AD54753D05B1B0A"},{"title":"디즈니+ 신작 <키스 식스 센스> <빌리가 리사를 만났을 때> 등 (다음 영화 ─ 매거진)","contents":"무비스트","link":"https://content.v.daum.net/v/Ex3zfqVPDc","retrieved":1653705931537,"image":"https://img1.daumcdn.net/thumb/S510x290/?fname=https%3A%2F%2Ft1.daumcdn.net%2Fnews%2F202205%2F28%2FMOVIST%2F20220528112250704olmn.jpg"},{"title":"<악의 꽃> 김철규 감독 X 넷플릭스 <셀러브리티> 제작 확정! (다음 영화 ─ 매거진)","contents":"무비스트","link":"https://content.v.daum.net/v/EcLggcuD1q","retrieved":1653705931539,"image":"https://img1.daumcdn.net/thumb/S510x290/?fname=https%3A%2F%2Ft1.daumcdn.net%2Fnews%2F202205%2F28%2FMOVIST%2F20220528112214317kghe.jpg"},{"title":"'브로커'·'마녀 2'·'헤어질 결심' 6월 극장 이끈다 (다음 영화 ─ 매거진)","contents":"알려줌 ALZi Media","link":"https://content.v.daum.net/v/EgD3vWBvzP","retrieved":1653705931544,"image":"https://img1.daumcdn.net/thumb/S510x290/?fname=https%3A%2F%2Ft1.daumcdn.net%2Fnews%2F202205%2F27%2Ffanzeel%2F20220527093800533wk8m.jpeg"},{"title":"아이유의 연기를 본 냉정한 해외평단의 반응이.. (다음 영화 ─ 매거진)","contents":"필더무비","link":"https://content.v.daum.net/v/En6VxG55ZK","retrieved":1653627059591,"image":"https://img1.daumcdn.net/thumb/S510x290/?fname=https%3A%2F%2Ft1.daumcdn.net%2Fnews%2F202205%2F27%2Ffeelthemovie%2F20220527031548951kvb4.jpeg"},{"title":"개봉 첫날 박스오피스1위! 꿈을 좇는 여성감독이 전하는 희망과 위로 (다음 영화 ─ 매거진)","contents":"맥스무비","link":"https://content.v.daum.net/v/ET0k3IPtwb","retrieved":1653627059593,"image":"https://img1.daumcdn.net/thumb/S510x290/?fname=https%3A%2F%2Ft1.daumcdn.net%2Fnews%2F202205%2F27%2Fmaxmovie%2F202205270328564496ec8.jpeg"},{"title":"12분이나 기립박수 이끌어낸 <브로커>, 어떤 평가 받았을까 (다음 영화 ─ 매거진)","contents":"맥스무비","link":"https://content.v.daum.net/v/Eff60R2CZ3","retrieved":1653627059597,"image":"https://img1.daumcdn.net/thumb/S510x290/?fname=https%3A%2F%2Ft1.daumcdn.net%2Fnews%2F202205%2F27%2Fmaxmovie%2F20220527122051564raty.jpg"},{"title":"진짜 사귀나? 열애설 나오자 두 배우가 전한 의외의 답변 (다음 영화 ─ 매거진)","contents":"필더무비","link":"https://content.v.daum.net/v/EuvvBDy5rM","retrieved":1653627059599,"image":"https://img1.daumcdn.net/thumb/S510x290/?fname=https%3A%2F%2Ft1.daumcdn.net%2Fnews%2F202205%2F26%2Ffeelthemovie%2F20220526150302975xka2.jpeg"},{"title":"이번 토르의 '상의 탈의'가 울컥한 이유 (다음 영화 ─ 매거진)","contents":"삶은영화","link":"https://content.v.daum.net/v/E7CCsubVMd","retrieved":1653613181641,"image":"https://img1.daumcdn.net/thumb/S510x290/?fname=https%3A%2F%2Ft1.daumcdn.net%2Fnews%2F202205%2F27%2FBoiledMovie%2F20220527011024036we4p.png"},{"title":"첫 레드 카펫으로 칸의 여신이 된 한국배우..눈물흘린 이유 (다음 영화 ─ 매거진)","contents":"필더무비","link":"https://content.v.daum.net/v/ETOwybm2j3","retrieved":1653613181645,"image":"https://img1.daumcdn.net/thumb/S510x290/?fname=https%3A%2F%2Ft1.daumcdn.net%2Fnews%2F202205%2F26%2Ffeelthemovie%2F20220526223314608i0m2.jpeg"},{"title":"영화로 돌아오는 '전설의 로큰롤 슈퍼스타' (다음 영화 ─ 매거진)","contents":"삶은영화","link":"https://content.v.daum.net/v/Eqy1TrU8bs","retrieved":1653606809821,"image":"https://img1.daumcdn.net/thumb/S510x290/?fname=https%3A%2F%2Ft1.daumcdn.net%2Fnews%2F202205%2F26%2Fharmony%2F20220526070814700ceim.png"},{"title":"별의 히어로 스타맨 (다음 영화 ─ 매거진)","contents":"슈퍼히어로 스토리","link":"https://content.v.daum.net/v/E1H0Sw3jGQ","retrieved":1653578150506,"image":"https://img1.daumcdn.net/thumb/S510x290/?fname=https%3A%2F%2Ft1.daumcdn.net%2Fnews%2F202205%2F26%2Fhero_nitko%2F20220526145406503dqwp.jpeg"},{"title":"이정재 감독 데뷔작에 대한 해외 평단의 솔직&냉정한 반응 (다음 영화 ─ 매거진)","contents":"필더무비","link":"https://content.v.daum.net/v/Eqd3ymTwbf","retrieved":1653549228882,"image":"https://img1.daumcdn.net/thumb/S510x290/?fname=https%3A%2F%2Ft1.daumcdn.net%2Fnews%2F202205%2F25%2Ffeelthemovie%2F20220525225612544iccm.jpeg"},{"title":"누가봐도 진짜 잘 어울리는 연인같은 한중 배우 커플 (다음 영화 ─ 매거진)","contents":"필더무비","link":"https://content.v.daum.net/v/ED08hhbwU3","retrieved":1653549228883,"image":"https://img1.daumcdn.net/thumb/S510x290/?fname=https%3A%2F%2Ft1.daumcdn.net%2Fnews%2F202205%2F26%2Ffeelthemovie%2F202205260450366062myo.jpeg"},{"title":"연인 케미 폭발한 배우 커플, 비하인드 사진 대량 공개! (다음 영화 ─ 매거진)","contents":"맥스무비","link":"https://content.v.daum.net/v/EGb5VtZJ3g","retrieved":1653545842549,"image":"https://img1.daumcdn.net/thumb/S510x290/?fname=https%3A%2F%2Ft1.daumcdn.net%2Fnews%2F202205%2F26%2Fmaxmovie%2F20220526054033679azmw.jpeg"},{"title":"초면인데.. 유해진과 '딥키스'하고 찐친되었다는 배우 (다음 영화 ─ 매거진)","contents":"삶은영화","link":"https://content.v.daum.net/v/ECzLyrzKBA","retrieved":1653542307349,"image":"https://img1.daumcdn.net/thumb/S510x290/?fname=https%3A%2F%2Ft1.daumcdn.net%2Fnews%2F202205%2F26%2FBoiledMovie%2F20220526024120232qots.png"},{"title":"원빈이 좋아해서 쫓아다녔던 미스 춘향 출신의 배우 (다음 영화 ─ 매거진)","contents":"필더무비","link":"https://content.v.daum.net/v/Ek9ULcudTf","retrieved":1653535298934,"image":"https://img1.daumcdn.net/thumb/S510x290/?fname=https%3A%2F%2Ft1.daumcdn.net%2Fnews%2F202205%2F25%2Ffeelthemovie%2F20220525130400309ooep.jpeg"},{"title":"'데뷔 31년' 만에 첫 단독 주연 맡은 배우 (다음 영화 ─ 매거진)","contents":"알려줌 ALZi Media","link":"https://content.v.daum.net/v/ELZtNaPqMN","retrieved":1653535298935,"image":"https://img1.daumcdn.net/thumb/S510x290/?fname=https%3A%2F%2Ft1.daumcdn.net%2Fnews%2F202205%2F25%2Ffanzeel%2F20220525100144503ajf0.jpeg"},{"title":"가짜 같은 진짜! <윤시내가 사라졌다> (다음 영화 ─ 매거진)","contents":"무비스트","link":"https://content.v.daum.net/v/Ezbf8C9eUl","retrieved":1653535298936,"image":"https://img1.daumcdn.net/thumb/S510x290/?fname=https%3A%2F%2Ft1.daumcdn.net%2Fnews%2F202205%2F26%2FMOVIST%2F20220526013005424kzsc.jpeg"},{"title":"조국사태를 다룬 첫 다큐 -<그대가 조국> (다음 영화 ─ 매거진)","contents":"무비스트","link":"https://content.v.daum.net/v/Eelw5zR25S","retrieved":1653639431845,"image":"https://img1.daumcdn.net/thumb/S510x290/?fname=https%3A%2F%2Ft1.daumcdn.net%2Fnews%2F202205%2F26%2FMOVIST%2F20220526012624170irpc.jpeg"},{"title":"영화인, 영화관, 영화를 향한 오마주 <오마주> (다음 영화 ─ 매거진)","contents":"무비스트","link":"https://content.v.daum.net/v/EoiFrYiSnU","retrieved":1653639431847,"image":"https://img1.daumcdn.net/thumb/S510x290/?fname=https%3A%2F%2Ft1.daumcdn.net%2Fnews%2F202205%2F26%2FMOVIST%2F20220526012344385xke2.jpeg"},{"title":"<브로크백 마운틴>보편적이면서도 보편적이지 않은 이야기 (다음 영화 ─ 브런치)","contents":"<span class=\"ico_movie ico_by\">by</span>사서 유","link":"https://brunch.co.kr/@@1xRj/175","retrieved":1653639438762,"image":"https://img1.daumcdn.net/thumb/S510x290/?fname=http%3A%2F%2Ft1.daumcdn.net%2Fbrunch%2Fservice%2Fuser%2F1xRj%2Fimage%2FsFRxKFO0MKMaPcsqEZdQVhF1Emc.jpg"},{"title":"마법 같은 그들의 대화 (다음 영화 ─ 브런치)","contents":"<span class=\"ico_movie ico_by\">by</span>Robinsoon","link":"https://brunch.co.kr/@@Ww5/303","retrieved":1653620715096,"image":"https://img1.daumcdn.net/thumb/S510x290/?fname=http%3A%2F%2Ft1.daumcdn.net%2Fbrunch%2Fservice%2Fuser%2FWw5%2Fimage%2Fs1q9gVg40wSJ-v39hFQv2US7XG8.jpg"},{"title":"사바하 (다음 영화 ─ 브런치)","contents":"<span class=\"ico_movie ico_by\">by</span>권씀","link":"https://brunch.co.kr/@@3drv/1155","retrieved":1653620715098,"image":"https://img1.daumcdn.net/thumb/S510x290/?fname=http%3A%2F%2Ft1.daumcdn.net%2Fbrunch%2Fservice%2Fuser%2F3drv%2Fimage%2FVCQOEZh1LA_leXiP2g68adm9erI.jpg"},{"title":"다른 누구도 아닌, 나를 들여다봐. (다음 영화 ─ 브런치)","contents":"<span class=\"ico_movie ico_by\">by</span>유마치","link":"https://brunch.co.kr/@@6ZBw/18","retrieved":1653632274691,"image":"https://img1.daumcdn.net/thumb/S510x290/?fname=http%3A%2F%2Ft1.daumcdn.net%2Fbrunch%2Fservice%2Fuser%2F6ZBw%2Fimage%2FavSke76l8D5oHoiKQws3orAKrJI.jpg"},{"title":"판타지를 가장한 하이퍼 리얼리즘 영화 <헝거게임> (다음 영화 ─ 브런치)","contents":"<span class=\"ico_movie ico_by\">by</span>달밤","link":"https://brunch.co.kr/@@4UOI/6","retrieved":1653632274702,"image":"https://img1.daumcdn.net/thumb/S510x290/?fname=http%3A%2F%2Ft1.daumcdn.net%2Fbrunch%2Fservice%2Fuser%2F4UOI%2Fimage%2FZz0VXV8OqbgnM87z0YnMY6QtjqM.jpg"},{"title":"너무 일찍 어른이 되어버린 아이에게 (다음 영화 ─ 브런치)","contents":"<span class=\"ico_movie ico_by\">by</span>호은","link":"https://brunch.co.kr/@@dBy9/16","retrieved":1653632274702,"image":"https://img1.daumcdn.net/thumb/S510x290/?fname=http%3A%2F%2Ft1.daumcdn.net%2Fbrunch%2Fservice%2Fuser%2FdBy9%2Fimage%2F_Pdgsw1WLJ-gBlRtP1VBL1j_3hA.JPG"},{"title":"<더 노비스> 단단히 미쳐야만 미칠 수 있는 목표 (다음 영화 ─ 브런치)","contents":"<span class=\"ico_movie ico_by\">by</span>장혜령","link":"https://brunch.co.kr/@@6dyt/825","retrieved":1653639438789,"image":"https://img1.daumcdn.net/thumb/S510x290/?fname=http%3A%2F%2Ft1.daumcdn.net%2Fbrunch%2Fservice%2Fuser%2F6dyt%2Fimage%2FR0ZkXxaQwk0SVrxeQzGXewe5RhI.png"},{"title":"스스로 칼을 빼어든 자와 거울을 들어주는 이 (다음 영화 ─ 브런치)","contents":"<span class=\"ico_movie ico_by\">by</span>모운","link":"https://brunch.co.kr/@@dFLK/12","retrieved":1653632274703,"image":"https://img1.daumcdn.net/thumb/S510x290/?fname=http%3A%2F%2Ft1.daumcdn.net%2Fbrunch%2Fservice%2Fuser%2FdFLK%2Fimage%2Fn1KK0e15vfXOc66_LEr6P20Btk0"},{"title":"너희 무슬림 여자 대통령 본 적 있니? (다음 영화 ─ 브런치)","contents":"<span class=\"ico_movie ico_by\">by</span>Purple Promise","link":"https://brunch.co.kr/@@2QQy/3","retrieved":1653620715100,"image":"https://img1.daumcdn.net/thumb/S510x290/?fname=http%3A%2F%2Ft1.daumcdn.net%2Fbrunch%2Fservice%2Fuser%2F2QQy%2Fimage%2FYA2rBJOKB3_1L8IMsXv7m0OkYzo.jpg"},{"title":"로라 완델, <플레이그라운드> (다음 영화 ─ 브런치)","contents":"<span class=\"ico_movie ico_by\">by</span>정수","link":"https://brunch.co.kr/@@5c1Q/692","retrieved":1653639438800,"image":"https://img1.daumcdn.net/thumb/S510x290/?fname=http%3A%2F%2Ft1.daumcdn.net%2Fbrunch%2Fservice%2Fuser%2F5c1Q%2Fimage%2F1lnRU1ZARbzaNeDscs3w5AID25Y.jpg"},{"title":"포기하지 않는 용기가 주는 가치 (다음 영화 ─ 브런치)","contents":"<span class=\"ico_movie ico_by\">by</span>예령","link":"https://brunch.co.kr/@@1Hpw/25","retrieved":1653639438800,"image":"https://img1.daumcdn.net/thumb/S510x290/?fname=http%3A%2F%2Ft1.daumcdn.net%2Fbrunch%2Fservice%2Fuser%2F1Hpw%2Fimage%2FpYpLQhk1M5Q7-EW1vJZacaaHbEk.jpg"},{"title":"<브로크백 마운틴> - 이데올로기에 금지된 사랑 (다음 영화 ─ 브런치)","contents":"<span class=\"ico_movie ico_by\">by</span>강유현","link":"https://brunch.co.kr/@@907a/43","retrieved":1653639438800,"image":"https://img1.daumcdn.net/thumb/S510x290/?fname=http%3A%2F%2Ft1.daumcdn.net%2Fbrunch%2Fservice%2Fuser%2F907a%2Fimage%2FJqffsAZT3ZKgrh-DLvMUDq5Yj1A.jpg"},{"title":"일상을 벗어난 곳에 봄이 있었다 (다음 영화 ─ 브런치)","contents":"<span class=\"ico_movie ico_by\">by</span>박깐느","link":"https://brunch.co.kr/@@5XLb/126","retrieved":1653639438838,"image":"https://img1.daumcdn.net/thumb/S510x290/?fname=http%3A%2F%2Ft1.daumcdn.net%2Fbrunch%2Fservice%2Fuser%2F5XLb%2Fimage%2FzzZEEfmkiaxMXzSTbS13DMFzGP8.jpeg"},{"title":"붙잡을 수 있었고, 붙잡힐 수 있었던(영화:먼훗날우리) (다음 영화 ─ 브런치)","contents":"<span class=\"ico_movie ico_by\">by</span>HATE JELLY","link":"https://brunch.co.kr/@@71Q7/54","retrieved":1653553089097,"image":"https://img1.daumcdn.net/thumb/S510x290/?fname=http%3A%2F%2Ft1.daumcdn.net%2Fbrunch%2Fservice%2Fuser%2F71Q7%2Fimage%2FoK2dnBH-0PuibykBdWcaKxSuASA.jpg"},{"title":"<델마와 루이스> 도망이 아닌 탈출, 추락이 아닌 비행 (다음 영화 ─ 브런치)","contents":"<span class=\"ico_movie ico_by\">by</span>사서 유","link":"https://brunch.co.kr/@@1xRj/174","retrieved":1653553089098,"image":"https://img1.daumcdn.net/thumb/S510x290/?fname=http%3A%2F%2Ft1.daumcdn.net%2Fbrunch%2Fservice%2Fuser%2F1xRj%2Fimage%2FWMkAQmHGX6tcMWlf2FdNqR8laSM.jpg"},{"title":"고령화가족 (다음 영화 ─ 브런치)","contents":"<span class=\"ico_movie ico_by\">by</span>권씀","link":"https://brunch.co.kr/@@3drv/1154","retrieved":1653553089099,"image":"https://img1.daumcdn.net/thumb/S510x290/?fname=http%3A%2F%2Ft1.daumcdn.net%2Fbrunch%2Fservice%2Fuser%2F3drv%2Fimage%2F-F14YaoVBg4kAGyQuB4TMFL-ADg.jpg"},{"title":"기예르모 델 토로와 욕망 (다음 영화 ─ 브런치)","contents":"<span class=\"ico_movie ico_by\">by</span>돌고래","link":"https://brunch.co.kr/@@cMRj/33","retrieved":1653539261275,"image":"https://img1.daumcdn.net/thumb/S510x290/?fname=http%3A%2F%2Ft1.daumcdn.net%2Fbrunch%2Fservice%2Fuser%2FcMRj%2Fimage%2FX_jtr8S69gnggfWxIqaohI9a_js.jpg"},{"title":"혹시나 했어요.. 역시나... (다음 영화 ─ 브런치)","contents":"<span class=\"ico_movie ico_by\">by</span>조현준의 영화리뷰","link":"https://brunch.co.kr/@@bIdi/104","retrieved":1653542314346,"image":"https://img1.daumcdn.net/thumb/S510x290/?fname=http%3A%2F%2Ft1.daumcdn.net%2Fbrunch%2Fservice%2Fuser%2FbIdi%2Fimage%2Folw7vlJeiwcb_8NLs09d8YIns00.jpeg"},{"title":"한국형 히어로의 귀환 (다음 영화 ─ 브런치)","contents":"<span class=\"ico_movie ico_by\">by</span>박준희","link":"https://brunch.co.kr/@@76sF/364","retrieved":1653542314347,"image":"https://img1.daumcdn.net/thumb/S510x290/?fname=http%3A%2F%2Ft1.daumcdn.net%2Fbrunch%2Fservice%2Fuser%2F76sF%2Fimage%2FZX3bU5T7m9-8fR624G64wI-qBWY.jpg"},{"title":"불화와 불화하며 (다음 영화 ─ 브런치)","contents":"<span class=\"ico_movie ico_by\">by</span>선이정","link":"https://brunch.co.kr/@@rsA/254","retrieved":1653542314348,"image":"https://img1.daumcdn.net/thumb/S510x290/?fname=http%3A%2F%2Ft1.daumcdn.net%2Fbrunch%2Fservice%2Fuser%2FrsA%2Fimage%2F-UWOWw9JqR9kYsRt-LKPk2uwcQw.jpeg"}]}