{"title":"[다음영화] 넷플릭스 ─ 공개예정","url":"https://movie.daum.net/premovie/netflix?flag=Y","favicon":"https://movie.daum.net/premovie/favicon.ico","elements":[{"title":"우박 맞은 날","contents":"22.03.30","link":"https://movie.daum.net/moviedb/main?movieId=158662","retrieved":1648448517193,"image":"https://img1.daumcdn.net/thumb/C408x596/?fname=https%3A%2F%2Ft1.daumcdn.net%2Fmovie%2F1b23a5fe89f80000bcb146922ff04656bc68183c"},{"title":"스웨어넷 라이브","contents":"22.03.30","link":"https://movie.daum.net/moviedb/main?movieId=129524","retrieved":1648617374143,"image":"https://img1.daumcdn.net/thumb/C408x596/?fname=http%3A%2F%2Ft1.daumcdn.net%2Fmovie%2Fa61a64fd819d4fac83c30772de546d421551960705863"},{"title":"스웨어넷 - 더 무비","contents":"22.03.30","link":"https://movie.daum.net/moviedb/main?movieId=129632","retrieved":1648617374144,"image":"https://img1.daumcdn.net/thumb/C408x596/?fname=http%3A%2F%2Ft1.daumcdn.net%2Fmovie%2F8013f85b868f4f4abd901b4c416be76d1552224646309"},{"title":"애프터 썬셋","contents":"22.04.01","link":"https://movie.daum.net/moviedb/main?movieId=40852","retrieved":1646716530783,"image":"https://img1.daumcdn.net/thumb/C408x596/?fname=http%3A%2F%2Ft1.daumcdn.net%2Fcfile%2F166C8B254C3180952B"},{"title":"더 버블","contents":"22.04.01","link":"https://movie.daum.net/moviedb/main?movieId=151513","retrieved":1647498059315,"image":"https://img1.daumcdn.net/thumb/C408x596/?fname=https%3A%2F%2Ft1.daumcdn.net%2Fmovie%2F064f740d53cc0c88023ff630847545cf092e1f63"},{"title":"아폴로 10 1/2 - 스페이스 에이지 어드벤처","contents":"22.04.01","link":"https://movie.daum.net/moviedb/main?movieId=147110","retrieved":1647573610768,"image":"https://img1.daumcdn.net/thumb/C408x596/?fname=https%3A%2F%2Ft1.daumcdn.net%2Fmovie%2F07cf946b97cb3bbbe9ede58457b8469097e318ab"},{"title":"배틀: 프리스타일","contents":"22.04.01","link":"https://movie.daum.net/moviedb/main?movieId=158731","retrieved":1648448517199},{"title":"극장판 : 타이거 앤 버니","contents":"22.04.01","link":"https://movie.daum.net/moviedb/main?movieId=74845","retrieved":1648448517199,"image":"https://img1.daumcdn.net/thumb/C408x596/?fname=http%3A%2F%2Ft1.daumcdn.net%2Fcfile%2F25561E50510757DF22"},{"title":"극장판 : 타이거 앤 버니 -더 라이징-","contents":"22.04.01","link":"https://movie.daum.net/moviedb/main?movieId=84153","retrieved":1648448517199,"image":"https://img1.daumcdn.net/thumb/C408x596/?fname=http%3A%2F%2Ft1.daumcdn.net%2Fcfile%2F25212D3E539910ED08"},{"title":"나의 흑역사 로맨티카 3","contents":"22.04.01","link":"https://movie.daum.net/moviedb/main?movieId=157981","retrieved":1648448517205,"image":"https://img1.daumcdn.net/thumb/C408x596/?fname=https%3A%2F%2Ft1.daumcdn.net%2Fmovie%2Fe2d70a5fc37dd0e65d5d5b818864ec20e87e32ac"},{"title":"십개월의 미래","contents":"22.04.04","link":"https://movie.daum.net/moviedb/main?movieId=141859","retrieved":1647573610769,"image":"https://img1.daumcdn.net/thumb/C408x596/?fname=https%3A%2F%2Ft1.daumcdn.net%2Fmovie%2F181a5fcef97d3f3084c4a69edb05cbd464af3b4f"},{"title":"시작은 키스 !","contents":"22.04.04","link":"https://movie.daum.net/moviedb/main?movieId=68767","retrieved":1648448517207,"image":"https://img1.daumcdn.net/thumb/C408x596/?fname=https%3A%2F%2Ft1.daumcdn.net%2Fmovie%2F4844785219cdeceaf6c3d52874ec5740ec444f70"},{"title":"리턴 투 스페이스","contents":"22.04.07","link":"https://movie.daum.net/moviedb/main?movieId=157577","retrieved":1648607879764,"image":"https://img1.daumcdn.net/thumb/C408x596/?fname=https%3A%2F%2Ft1.daumcdn.net%2Fmovie%2F10dda01eb940da5d5fa3e0c1460fb8b59ab697af"},{"title":"야차","contents":"22.04.08","link":"https://movie.daum.net/moviedb/main?movieId=133674","retrieved":1647580566175,"image":"https://img1.daumcdn.net/thumb/C408x596/?fname=https%3A%2F%2Ft1.daumcdn.net%2Fmovie%2F4f71c6ce6a6e6ca5f72b3cf4de1a528a80f49df5"},{"title":"댄싱 온 글래스","contents":"22.04.08","link":"https://movie.daum.net/moviedb/main?movieId=158603","retrieved":1647573610770,"image":"https://img1.daumcdn.net/thumb/C408x596/?fname=https%3A%2F%2Ft1.daumcdn.net%2Fmovie%2Fa2f11dfbee11ad92d9ddc289b9d23900825eb5eb"},{"title":"메탈 로드","contents":"22.04.08","link":"https://movie.daum.net/moviedb/main?movieId=158667","retrieved":1648448517215,"image":"https://img1.daumcdn.net/thumb/C408x596/?fname=https%3A%2F%2Ft1.daumcdn.net%2Fmovie%2F157ff4210073ba42de345e2f5de37632fafad614"},{"title":"인 비트윈","contents":"22.04.08","link":"https://movie.daum.net/moviedb/main?movieId=157284","retrieved":1648448517219,"image":"https://img1.daumcdn.net/thumb/C408x596/?fname=https%3A%2F%2Ft1.daumcdn.net%2Fmovie%2Fcdc136eb6dc107c8ec4950f7cac75e5331df0d92"}]}