{"title":"[다음영화] 왓챠 ─ 종료예정","url":"https://movie.daum.net/premovie/watcha?flag=C","favicon":"https://movie.daum.net/premovie/favicon.ico","elements":[{"title":"더 케이지","contents":"23.01.29","link":"https://movie.daum.net/moviedb/main?movieId=132987","retrieved":1673820669308,"image":"https://img1.daumcdn.net/thumb/C408x596/?fname=http%3A%2F%2Ft1.daumcdn.net%2Fmovie%2F85ee3cfc8cf24587990ae43db22ab4f51561814600793"},{"title":"폼페이: 최후의 날","contents":"23.01.29","link":"https://movie.daum.net/moviedb/main?movieId=82025","retrieved":1673916885106,"image":"https://img1.daumcdn.net/thumb/C408x596/?fname=http%3A%2F%2Ft1.daumcdn.net%2Fcfile%2F2230184A52FBEFCC12"},{"title":"무드 인디고","contents":"23.01.30","link":"https://movie.daum.net/moviedb/main?movieId=72496","retrieved":1673907054401,"image":"https://img1.daumcdn.net/thumb/C408x596/?fname=http%3A%2F%2Ft1.daumcdn.net%2Fcfile%2F22766E4B5473D66B05"},{"title":"스탠바이 캅","contents":"23.01.30","link":"https://movie.daum.net/moviedb/main?movieId=53680","retrieved":1674083524289,"image":"https://img1.daumcdn.net/thumb/C408x596/?fname=http%3A%2F%2Ft1.daumcdn.net%2Fcfile%2F1373940F4C58C7D278"},{"title":"에이스 벤츄라","contents":"23.01.30","link":"https://movie.daum.net/moviedb/main?movieId=16149","retrieved":1674083524289,"image":"https://img1.daumcdn.net/thumb/C408x596/?fname=http%3A%2F%2Ft1.daumcdn.net%2Fcfile%2F156F1B10AE3B69D121"},{"title":"크레이머 대 크레이머","contents":"23.01.30","link":"https://movie.daum.net/moviedb/main?movieId=3318","retrieved":1674083524290,"image":"https://img1.daumcdn.net/thumb/C408x596/?fname=http%3A%2F%2Ft1.daumcdn.net%2Fcfile%2F133CE6214BF0F3D4BE"},{"title":"도니 브래스코","contents":"23.01.30","link":"https://movie.daum.net/moviedb/main?movieId=1833","retrieved":1674083524290,"image":"https://img1.daumcdn.net/thumb/C408x596/?fname=http%3A%2F%2Ft1.daumcdn.net%2Fcfile%2F14492F10B26EA50FF9"},{"title":"에이스 벤츄라 2","contents":"23.01.30","link":"https://movie.daum.net/moviedb/main?movieId=17248","retrieved":1674083524292,"image":"https://img1.daumcdn.net/thumb/C408x596/?fname=http%3A%2F%2Ft1.daumcdn.net%2Fcfile%2F16276B2E4CE4A91A1B"},{"title":"본 콜렉터","contents":"23.01.30","link":"https://movie.daum.net/moviedb/main?movieId=1884","retrieved":1674083524292,"image":"https://img1.daumcdn.net/thumb/C408x596/?fname=http%3A%2F%2Ft1.daumcdn.net%2Fcfile%2F146F1B10AC0BB921B0"},{"title":"배드 티처","contents":"23.01.30","link":"https://movie.daum.net/moviedb/main?movieId=55091","retrieved":1674083524292,"image":"https://img1.daumcdn.net/thumb/C408x596/?fname=http%3A%2F%2Ft1.daumcdn.net%2Fcfile%2F277A6541519DA0D630"},{"title":"스타쉽 트루퍼스 3","contents":"23.01.30","link":"https://movie.daum.net/moviedb/main?movieId=44614","retrieved":1674083524292,"image":"https://img1.daumcdn.net/thumb/C408x596/?fname=http%3A%2F%2Ft1.daumcdn.net%2Fcfile%2F1711F2154A28A50201"},{"title":"대디 데이 케어","contents":"23.01.30","link":"https://movie.daum.net/moviedb/main?movieId=36618","retrieved":1674083524293,"image":"https://img1.daumcdn.net/thumb/C408x596/?fname=http%3A%2F%2Ft1.daumcdn.net%2Fcfile%2F13290910FECAFCD508"},{"title":"그로운 업스 2","contents":"23.01.30","link":"https://movie.daum.net/moviedb/main?movieId=70982","retrieved":1674184496967,"image":"https://img1.daumcdn.net/thumb/C408x596/?fname=http%3A%2F%2Ft1.daumcdn.net%2Fcfile%2F216C0B38519F247515"},{"title":"호스텔 3","contents":"23.01.30","link":"https://movie.daum.net/moviedb/main?movieId=69172","retrieved":1674083524293,"image":"https://img1.daumcdn.net/thumb/C408x596/?fname=http%3A%2F%2Ft1.daumcdn.net%2Fcfile%2F1520B0334F0E40C703"},{"title":"레스트리스","contents":"23.01.30","link":"https://movie.daum.net/moviedb/main?movieId=54017","retrieved":1674083524293,"image":"https://img1.daumcdn.net/thumb/C408x596/?fname=http%3A%2F%2Ft1.daumcdn.net%2Fcfile%2F20645B3F4E814FFC1E"},{"title":"다 큰 녀석들","contents":"23.01.30","link":"https://movie.daum.net/moviedb/main?movieId=50896","retrieved":1674083524293,"image":"https://img1.daumcdn.net/thumb/C408x596/?fname=http%3A%2F%2Ft1.daumcdn.net%2Fcfile%2F153BA4474E829E8B1E"},{"title":"브로큰 하츠 갤러리","contents":"23.01.30","link":"https://movie.daum.net/moviedb/main?movieId=142664","retrieved":1674083524293,"image":"https://img1.daumcdn.net/thumb/C408x596/?fname=https%3A%2F%2Ft1.daumcdn.net%2Fmovie%2F52d700ebf9de15aeb39d4be9bc57f1fe3c79c52f"},{"title":"스텝 브라더스","contents":"23.01.30","link":"https://movie.daum.net/moviedb/main?movieId=45022","retrieved":1674083524294,"image":"https://img1.daumcdn.net/thumb/C408x596/?fname=http%3A%2F%2Ft1.daumcdn.net%2Fcfile%2F1645BA164C2C3DC253"},{"title":"미지와의 조우","contents":"23.01.30","link":"https://movie.daum.net/moviedb/main?movieId=10251","retrieved":1674083524294,"image":"https://img1.daumcdn.net/thumb/C408x596/?fname=http%3A%2F%2Ft1.daumcdn.net%2Fcfile%2F14498110B159FD8671"},{"title":"스튜어트 리틀 3","contents":"23.01.30","link":"https://movie.daum.net/moviedb/main?movieId=45391","retrieved":1674083524296,"image":"https://img1.daumcdn.net/thumb/C408x596/?fname=http%3A%2F%2Ft1.daumcdn.net%2Fcfile%2F120D7C10AD571391B0"},{"title":"애프터 쇼크","contents":"23.01.31","link":"https://movie.daum.net/moviedb/main?movieId=72379","retrieved":1674083524296,"image":"https://img1.daumcdn.net/thumb/C408x596/?fname=http%3A%2F%2Ft1.daumcdn.net%2Fcfile%2F2559F44553BF27FB0E"},{"title":"체르노빌 다이어리","contents":"23.01.31","link":"https://movie.daum.net/moviedb/main?movieId=70844","retrieved":1673993493345,"image":"https://img1.daumcdn.net/thumb/C408x596/?fname=http%3A%2F%2Ft1.daumcdn.net%2Fcfile%2F2118E14C52D3A4FC37"},{"title":"시스터","contents":"23.01.31","link":"https://movie.daum.net/moviedb/main?movieId=69510","retrieved":1674169946839,"image":"https://img1.daumcdn.net/thumb/C408x596/?fname=http%3A%2F%2Ft1.daumcdn.net%2Fcfile%2F13012E4A5000899F33"},{"title":"리틀 뱀파이어","contents":"23.01.31","link":"https://movie.daum.net/moviedb/main?movieId=116149","retrieved":1673993493346,"image":"https://img1.daumcdn.net/thumb/C408x596/?fname=http%3A%2F%2Ft1.daumcdn.net%2Fmovie%2F94c10ca3cf012e93b94dd4d8fb5ba42427278568"},{"title":"수상한 가족","contents":"23.01.31","link":"https://movie.daum.net/moviedb/main?movieId=56938","retrieved":1673993493348,"image":"https://img1.daumcdn.net/thumb/C408x596/?fname=http%3A%2F%2Ft1.daumcdn.net%2Fcfile%2F2773644951D274EB3A"},{"title":"쿵푸 몽키","contents":"23.01.31","link":"https://movie.daum.net/moviedb/main?movieId=117670","retrieved":1673993493349,"image":"https://img1.daumcdn.net/thumb/C408x596/?fname=http%3A%2F%2Ft1.daumcdn.net%2Fmovie%2F63853676aa52956ed756b9219102206bb130bce0"},{"title":"극장판 포켓몬스터DP 아르세우스 초극의 시공으로","contents":"23.01.31","link":"https://movie.daum.net/moviedb/main?movieId=52733","retrieved":1673993493351,"image":"https://img1.daumcdn.net/thumb/C408x596/?fname=http%3A%2F%2Ft1.daumcdn.net%2Fcfile%2F2018D3044B1DE73803"},{"title":"엑소시스트: 악마의 영혼","contents":"23.01.31","link":"https://movie.daum.net/moviedb/main?movieId=113311","retrieved":1674008309097,"image":"https://img1.daumcdn.net/thumb/C408x596/?fname=http%3A%2F%2Ft1.daumcdn.net%2Fmovie%2F00ead5727f46388681883684a3c70c8f5031f97a"},{"title":"분노의 질주: 더 세븐","contents":"23.02.06","link":"https://movie.daum.net/moviedb/main?movieId=80723","retrieved":1674511869731,"image":"https://img1.daumcdn.net/thumb/C408x596/?fname=http%3A%2F%2Ft1.daumcdn.net%2Fmovie%2Fc9018970c380aa85c896ad27ccefa0708d3bbeda"},{"title":"분노의 질주: 더 익스트림","contents":"23.02.06","link":"https://movie.daum.net/moviedb/main?movieId=100649","retrieved":1674511869732,"image":"https://img1.daumcdn.net/thumb/C408x596/?fname=https%3A%2F%2Ft1.daumcdn.net%2Fmovie%2F21c2689868817dd287dad56ef83f7458979374ce"},{"title":"마이 골든 데이즈","contents":"23.02.08","link":"https://movie.daum.net/moviedb/main?movieId=95098","retrieved":1674706425703,"image":"https://img1.daumcdn.net/thumb/C408x596/?fname=http%3A%2F%2Ft1.daumcdn.net%2Fmovie%2Fef72cc9bc1a43dcc578d2ab136242f4cd747a987"}]}