{"title":"다음 영화 ─ 매거진","url":"https://movie.daum.net/contents/1boon","favicon":"https://movie.daum.net/contents/favicon.ico","elements":[{"title":"두 남자배우가 함께 손 잡고 해외로 떠난 이유","contents":"맥스무비","link":"https://v.daum.net/v/18k8meatTg","retrieved":1693512691111,"image":"https://img1.daumcdn.net/thumb/S510x290/?fname=https%3A%2F%2Ft1.daumcdn.net%2Fnews%2F202309%2F01%2Fmaxmovie%2F20230901050006175wjhk.jpg"},{"title":"알고 보니 '힘숨찐'이었다는 최근 가장 핫한 '배우'","contents":"맥스무비","link":"https://v.daum.net/v/yvp1nb6hAH","retrieved":1693512691115,"image":"https://img1.daumcdn.net/thumb/S510x290/?fname=https%3A%2F%2Ft1.daumcdn.net%2Fnews%2F202309%2F01%2Fmaxmovie%2F20230901043017118qmym.jpg"},{"title":"'깜짝' 친분의 두 스타! 찐한 '우정' 계기 알고 보니...","contents":"맥스무비","link":"https://v.daum.net/v/Yqm5yjmBDI","retrieved":1693494654765,"image":"https://img1.daumcdn.net/thumb/S510x290/?fname=https%3A%2F%2Ft1.daumcdn.net%2Fnews%2F202309%2F01%2Fmaxmovie%2F20230901000015423vopq.jpg"},{"title":"'너무 귀하다'는 투샷 안무 영상 공개한 171cm 미녀배우","contents":"삶은영화","link":"https://v.daum.net/v/YIe9HlHRcy","retrieved":1693480183044,"image":"https://img1.daumcdn.net/thumb/S510x290/?fname=https%3A%2F%2Ft1.daumcdn.net%2Fnews%2F202308%2F31%2FBoiledMovie%2F20230831195005385myaa.png"},{"title":"칭챙총? 인종혐오한 백인소년에게 주먹을 날린 소녀","contents":"삶은영화","link":"https://v.daum.net/v/QvVF6FqkgH","retrieved":1693473073114,"image":"https://img1.daumcdn.net/thumb/S510x290/?fname=https%3A%2F%2Ft1.daumcdn.net%2Fnews%2F202308%2F31%2FBoiledMovie%2F20230831174433553oebt.png"},{"title":"동남아에 펜션을 짓기 위해 열일중이라는 연예인","contents":"필더무비","link":"https://v.daum.net/v/GKkOZwlfrH","retrieved":1693469653945,"image":"https://img1.daumcdn.net/thumb/S510x290/?fname=https%3A%2F%2Ft1.daumcdn.net%2Fnews%2F202308%2F31%2Ffeelthemovie%2F20230831171005871atlx.jpg"},{"title":"알고 보니 '대단한 가문'의 막내딸이었다는 배우","contents":"맥스무비","link":"https://v.daum.net/v/zOjCEQnXAK","retrieved":1693469653947,"image":"https://img1.daumcdn.net/thumb/S510x290/?fname=https%3A%2F%2Ft1.daumcdn.net%2Fnews%2F202308%2F31%2Fmaxmovie%2F20230831175029141juxz.jpg"},{"title":"최근 기분 너무 좋아서 하늘 나는 기분이라는 배우","contents":"맥스무비","link":"https://v.daum.net/v/8VvwzT5JCl","retrieved":1693465843588,"image":"https://img1.daumcdn.net/thumb/S510x290/?fname=https%3A%2F%2Ft1.daumcdn.net%2Fnews%2F202308%2F31%2Fmaxmovie%2F20230831153512271ywwr.jpg"},{"title":"너무 예쁜데 키 크고 태권도 4단인 무결점 여고생 근황","contents":"필더무비","link":"https://v.daum.net/v/zQ6cf5ujJb","retrieved":1693458629478,"image":"https://img1.daumcdn.net/thumb/S510x290/?fname=https%3A%2F%2Ft1.daumcdn.net%2Fnews%2F202308%2F31%2Ffeelthemovie%2F20230831135503556nffb.jpg"},{"title":"'오펜하이머' 배우가 여장을 한 적이 있었다?","contents":"알려줌 ALZi Media","link":"https://v.daum.net/v/4lQ5HXpai8","retrieved":1693455187167,"image":"https://img1.daumcdn.net/thumb/S510x290/?fname=https%3A%2F%2Ft1.daumcdn.net%2Fnews%2F202308%2F31%2Ffanzeel%2F20230831125006229woeg.jpg"},{"title":"혼자서 해외 여행중? 호주서 갑자기 포착된 국민 아이돌","contents":"필더무비","link":"https://v.daum.net/v/KpWbYxLZAT","retrieved":1693451497018,"image":"https://img1.daumcdn.net/thumb/S510x290/?fname=https%3A%2F%2Ft1.daumcdn.net%2Fnews%2F202308%2F31%2Ffeelthemovie%2F20230831114418673vbos.jpg"},{"title":"분장 벗고 생얼로 복귀한 흥행수익 13조 여배우","contents":"삶은영화","link":"https://v.daum.net/v/zEX1ujmBDE","retrieved":1693448267026,"image":"https://img1.daumcdn.net/thumb/S510x290/?fname=https%3A%2F%2Ft1.daumcdn.net%2Fnews%2F202308%2F31%2FBoiledMovie%2F20230831110644771bafc.png"},{"title":"국모의 상을 지녔다며 캐스팅된 단역 배우 놀라운 정체","contents":"필더무비","link":"https://v.daum.net/v/Xsz6cjmBC1","retrieved":1693442646023,"image":"https://img1.daumcdn.net/thumb/S510x290/?fname=https%3A%2F%2Ft1.daumcdn.net%2Fnews%2F202308%2F31%2Ffeelthemovie%2F20230831093005628jjsr.jpg"},{"title":"서태지가 보자마자 반해서 바로 러브콜 한 여배우","contents":"필더무비","link":"https://v.daum.net/v/WtF4xPiHf3","retrieved":1693437043150,"image":"https://img1.daumcdn.net/thumb/S510x290/?fname=https%3A%2F%2Ft1.daumcdn.net%2Fnews%2F202308%2F31%2Ffeelthemovie%2F20230831081006592zrbq.jpg"},{"title":"현재 해외에서 가장 잘나가는 한국감독들, 그 이유는...","contents":"맥스무비","link":"https://v.daum.net/v/UXk1hOyPao","retrieved":1693437043150,"image":"https://img1.daumcdn.net/thumb/S510x290/?fname=https%3A%2F%2Ft1.daumcdn.net%2Fnews%2F202308%2F31%2Fmaxmovie%2F20230831080025923ltqk.jpg"},{"title":"17년 전, 일본이 침몰한다는 내용 담은 영화","contents":"알려줌 ALZi Media","link":"https://v.daum.net/v/44nVxMo5Am","retrieved":1693437043150,"image":"https://img1.daumcdn.net/thumb/S510x290/?fname=https%3A%2F%2Ft1.daumcdn.net%2Fnews%2F202308%2F31%2Ffanzeel%2F20230831075006507jath.jpg"},{"title":"할리우드 대표 친한파 배우가 전한 '깜짝' 소식!","contents":"맥스무비","link":"https://v.daum.net/v/9pnsMPiHOz","retrieved":1693433413432,"image":"https://img1.daumcdn.net/thumb/S510x290/?fname=https%3A%2F%2Ft1.daumcdn.net%2Fnews%2F202308%2F31%2Fmaxmovie%2F20230831070016131rhlw.jpg"},{"title":"결국 세계1위 찍은! 대한민국의 두 남녀, 공개된 사진 보니...","contents":"맥스무비","link":"https://v.daum.net/v/Bwzoqu2mD7","retrieved":1693426434280,"image":"https://img1.daumcdn.net/thumb/S510x290/?fname=https%3A%2F%2Ft1.daumcdn.net%2Fnews%2F202308%2F31%2Fmaxmovie%2F20230831050005208afcx.jpg"},{"title":"송강호·강동원·하정우…추석 극장가 민심 잡을까?","contents":"알려줌 ALZi Media","link":"https://v.daum.net/v/q3CMy5ujy8","retrieved":1693390285206,"image":"https://img1.daumcdn.net/thumb/S510x290/?fname=https%3A%2F%2Ft1.daumcdn.net%2Fnews%2F202308%2F30%2Ffanzeel%2F20230830181228094byyg.jpg"},{"title":"자기가 죽으면 옥수수밭에 뭍어 달라한 여배우","contents":"필더무비","link":"https://v.daum.net/v/un2GW2xvBi","retrieved":1693383250392,"image":"https://img1.daumcdn.net/thumb/S510x290/?fname=https%3A%2F%2Ft1.daumcdn.net%2Fnews%2F202308%2F30%2Ffeelthemovie%2F20230830171133033ayth.jpg"}]}