{"title":"다음 영화 ─ 매거진","url":"https://movie.daum.net/contents/1boon","favicon":"https://movie.daum.net/contents/favicon.ico","elements":[{"title":"'마녀'에서 싸늘한 눈빛이 인상적이던 그 배우 근황","contents":"삶은영화","link":"https://content.v.daum.net/v/2IT1SdS4TF","retrieved":1658272441865,"image":"https://img1.daumcdn.net/thumb/S510x290/?fname=https%3A%2F%2Ft1.daumcdn.net%2Fnews%2F202207%2F19%2FBoiledMovie%2F20220719225316131nsyp.png"},{"title":"'아침드라마'같은 이유! 넷플릭스 <블랙의 신부>","contents":"무비스트","link":"https://content.v.daum.net/v/PT1Y97o56t","retrieved":1658272441866,"image":"https://img1.daumcdn.net/thumb/S510x290/?fname=https%3A%2F%2Ft1.daumcdn.net%2Fnews%2F202207%2F19%2FMOVIST%2F20220719225032388chiw.jpeg"},{"title":"제작비 400억인 이 영화, 하마터면 크게 실패할뻔 했다","contents":"필더무비","link":"https://content.v.daum.net/v/BYnqobj34X","retrieved":1658214774146,"image":"https://img1.daumcdn.net/thumb/S510x290/?fname=https%3A%2F%2Ft1.daumcdn.net%2Fnews%2F202207%2F19%2Ffeelthemovie%2F20220719044954980nkyu.jpeg"},{"title":"윤여정에 상 안겼던 브래드 피트, 3년 만에 전한 반가운 소식!","contents":"맥스무비","link":"https://content.v.daum.net/v/xmZR5D3oCl","retrieved":1658211443406,"image":"https://img1.daumcdn.net/thumb/S510x290/?fname=https%3A%2F%2Ft1.daumcdn.net%2Fnews%2F202207%2F19%2Fmaxmovie%2F202207190536578292bzx.jpeg"},{"title":"그리스로 휴가 간 중년 교수에게 벌어진 일","contents":"알려줌 ALZi Media","link":"https://content.v.daum.net/v/Zq5PtrpajB","retrieved":1658202936180,"image":"https://img1.daumcdn.net/thumb/S510x290/?fname=https%3A%2F%2Ft1.daumcdn.net%2Fnews%2F202207%2F19%2Ffanzeel%2F20220719031532499p6lg.jpeg"},{"title":"남한에서 온 로또 당첨 영수증을 주운 북한군인의 반응","contents":"필더무비","link":"https://content.v.daum.net/v/KVkVPUWQgF","retrieved":1658202936186,"image":"https://img1.daumcdn.net/thumb/S510x290/?fname=https%3A%2F%2Ft1.daumcdn.net%2Fnews%2F202207%2F19%2Ffeelthemovie%2F20220719020624321umuh.jpeg"},{"title":"여배우가 무려 8시간 연기하고 실신한 문제 연기장면","contents":"필더무비","link":"https://content.v.daum.net/v/bLxDm1hVgG","retrieved":1658202936189,"image":"https://img1.daumcdn.net/thumb/S510x290/?fname=https%3A%2F%2Ft1.daumcdn.net%2Fnews%2F202207%2F18%2Ffeelthemovie%2F202207181328256646har.jpeg"},{"title":"8,90년대 사람들을 공포에 빠뜨린 이 붉은빛의 정체","contents":"필더무비","link":"https://content.v.daum.net/v/5fvsbnfOkM","retrieved":1658193191304,"image":"https://img1.daumcdn.net/thumb/S510x290/?fname=https%3A%2F%2Ft1.daumcdn.net%2Fnews%2F202207%2F18%2Ffeelthemovie%2F20220718125006041vsnd.jpeg"},{"title":"3,000명을 제치고 오디션 합격한 전설의 소녀의 근황","contents":"필더무비","link":"https://content.v.daum.net/v/X76dcYrqIN","retrieved":1658193191306,"image":"https://img1.daumcdn.net/thumb/S510x290/?fname=https%3A%2F%2Ft1.daumcdn.net%2Fnews%2F202207%2F18%2Ffeelthemovie%2F202207181221434441zcz.jpeg"},{"title":"한국영화 '마녀' 그대로 베껴 분노유발하는 중국영화","contents":"삶은영화","link":"https://content.v.daum.net/v/3oCU6XOKo0","retrieved":1658186001924,"image":"https://img1.daumcdn.net/thumb/S510x290/?fname=https%3A%2F%2Ft1.daumcdn.net%2Fnews%2F202207%2F18%2FBoiledMovie%2F20220718221805034kvq4.png"},{"title":"칸 영화제에서 관객들이 무려 22분간 박수친 이 영화","contents":"필더무비","link":"https://content.v.daum.net/v/HnWkfjxvIH","retrieved":1658128365262,"image":"https://img1.daumcdn.net/thumb/S510x290/?fname=https%3A%2F%2Ft1.daumcdn.net%2Fnews%2F202207%2F17%2Ffeelthemovie%2F20220717152653473qryr.jpeg"},{"title":"질긴 <오징어게임> 인연? 두 배우가 다시 만난 이유는..","contents":"맥스무비","link":"https://content.v.daum.net/v/VKJaKDJGQV","retrieved":1658128365263,"image":"https://img1.daumcdn.net/thumb/S510x290/?fname=https%3A%2F%2Ft1.daumcdn.net%2Fnews%2F202207%2F18%2Fmaxmovie%2F20220718070125987cxkm.jpeg"},{"title":"한국-미국 대표하는 시대의 아이콘들이 함께 전한 반가운 '소식'","contents":"맥스무비","link":"https://content.v.daum.net/v/5YXm6CNFSi","retrieved":1658128365265,"image":"https://img1.daumcdn.net/thumb/S510x290/?fname=https%3A%2F%2Ft1.daumcdn.net%2Fnews%2F202207%2F18%2Fmaxmovie%2F20220718065444835ntcd.jpeg"},{"title":"최근 딸 출산한 배우, 180도 달라진 모습으로 돌아왔는데..","contents":"맥스무비","link":"https://content.v.daum.net/v/pCw3L9tnDT","retrieved":1658128365266,"image":"https://img1.daumcdn.net/thumb/S510x290/?fname=https%3A%2F%2Ft1.daumcdn.net%2Fnews%2F202207%2F18%2Fmaxmovie%2F20220718064613478xp4p.jpeg"},{"title":"[7월 2주 국내 박스] <탑건: 매버릭> 선두 복귀! 573만명 돌파","contents":"무비스트","link":"https://content.v.daum.net/v/XXcQj8UNoy","retrieved":1658122031565,"image":"https://img1.daumcdn.net/thumb/S510x290/?fname=https%3A%2F%2Ft1.daumcdn.net%2Fnews%2F202207%2F18%2FMOVIST%2F20220718050823961joyk.jpeg"},{"title":"13세 소녀를 죽이라는 미션을 거절한 킬러","contents":"알려줌 ALZi Media","link":"https://content.v.daum.net/v/x9EouvkUrR","retrieved":1658115767968,"image":"https://img1.daumcdn.net/thumb/S510x290/?fname=https%3A%2F%2Ft1.daumcdn.net%2Fnews%2F202207%2F18%2Ffanzeel%2F20220718025847677o7zf.jpeg"},{"title":"이때는 몰랐는데..지금보니 초호화 캐스팅인 여배우들","contents":"필더무비","link":"https://content.v.daum.net/v/58ED3Qzchv","retrieved":1658115767969,"image":"https://img1.daumcdn.net/thumb/S510x290/?fname=https%3A%2F%2Ft1.daumcdn.net%2Fnews%2F202207%2F17%2Ffeelthemovie%2F20220717150705121r9ie.jpeg"},{"title":"일하다가 열애설이 나온 두 남녀스타가 보인 쿨한 반응","contents":"필더무비","link":"https://content.v.daum.net/v/xPOixwiHca","retrieved":1658115767971,"image":"https://img1.daumcdn.net/thumb/S510x290/?fname=https%3A%2F%2Ft1.daumcdn.net%2Fnews%2F202207%2F17%2Ffeelthemovie%2F202207171437075547igr.jpeg"},{"title":"아무리 봐도 미국 블록버스터 영화 같은 이 한국 영화","contents":"필더무비","link":"https://content.v.daum.net/v/4zOWMtlfxH","retrieved":1658106272460,"image":"https://img1.daumcdn.net/thumb/S510x290/?fname=https%3A%2F%2Ft1.daumcdn.net%2Fnews%2F202207%2F18%2Ffeelthemovie%2F20220718004340920edwt.jpeg"},{"title":"한국 여배우에게 매일 사랑한다고 고백한 중화권 스타","contents":"필더무비","link":"https://content.v.daum.net/v/bN9VXso5AG","retrieved":1658106272462,"image":"https://img1.daumcdn.net/thumb/S510x290/?fname=https%3A%2F%2Ft1.daumcdn.net%2Fnews%2F202207%2F17%2Ffeelthemovie%2F20220717134404039ng5z.jpeg"}]}