{"title":"다음영화 영화관 ─ 개봉예정","url":"https://movie.daum.net/premovie/theater?flag=C","favicon":"https://movie.daum.net/premovie/favicon.ico","elements":[{"title":"위시","contents":"24.01.03","link":"https://movie.daum.net/moviedb/main?movieId=169932","retrieved":1703205937001,"image":"https://img1.daumcdn.net/thumb/C408x596/?fname=https%3A%2F%2Ft1.daumcdn.net%2Fmovie%2F408f94707f226e97f829cbabcab8b6aa9e8cbd07"},{"title":"외계+인 2부","contents":"24.01.10","link":"https://movie.daum.net/moviedb/main?movieId=174565","retrieved":1703632306249,"image":"https://img1.daumcdn.net/thumb/C408x596/?fname=https%3A%2F%2Ft1.daumcdn.net%2Fmovie%2Fa22468266e53007502088cba1ad3d4801604fd47"},{"title":"길위에 김대중","contents":"24.01.10","link":"https://movie.daum.net/moviedb/main?movieId=174676","retrieved":1702530631092,"image":"https://img1.daumcdn.net/thumb/C408x596/?fname=https%3A%2F%2Ft1.daumcdn.net%2Fmovie%2F6995658a64157d6f100879eb73ea2e0be1f6f9c2"},{"title":"클레오의 세계","contents":"24.01.03","link":"https://movie.daum.net/moviedb/main?movieId=171062","retrieved":1703032686867,"image":"https://img1.daumcdn.net/thumb/C408x596/?fname=https%3A%2F%2Ft1.daumcdn.net%2Fmovie%2F29a5b579c9003b003529ef87109a113175157f47"},{"title":"인투 더 월드","contents":"24.01.10","link":"https://movie.daum.net/moviedb/main?movieId=172319","retrieved":1702998650250,"image":"https://img1.daumcdn.net/thumb/C408x596/?fname=https%3A%2F%2Ft1.daumcdn.net%2Fmovie%2F1f54b880c3f8d0b778020beffe7a167373e212f0"},{"title":"부활 그 소망","contents":"24.02","link":"https://movie.daum.net/moviedb/main?movieId=174463","retrieved":1703032686869,"image":"https://img1.daumcdn.net/thumb/C408x596/?fname=https%3A%2F%2Ft1.daumcdn.net%2Fmovie%2Fb678500a3749c949f5334b15445efd4313509a52"},{"title":"우리 돈 벌레","contents":"23.12.28","link":"https://movie.daum.net/moviedb/main?movieId=171368","retrieved":1703131961294,"image":"https://img1.daumcdn.net/thumb/C408x596/?fname=https%3A%2F%2Ft1.daumcdn.net%2Fmovie%2Fe0bc28e9c1332f9e848807958cbc4e983c6035c0"},{"title":"그리고, 살아간다","contents":"24.01.01","link":"https://movie.daum.net/moviedb/main?movieId=147081","retrieved":1703153474036,"image":"https://img1.daumcdn.net/thumb/C408x596/?fname=https%3A%2F%2Ft1.daumcdn.net%2Fmovie%2Ff1976b289037871ad8ef6dd1369c52c06244a600"},{"title":"칼라스-파리, 1958","contents":"24.01.04","link":"https://movie.daum.net/moviedb/main?movieId=176368","retrieved":1703119558953},{"title":"립세의 사계","contents":"24.01.10","link":"https://movie.daum.net/moviedb/main?movieId=173621","retrieved":1703632306249,"image":"https://img1.daumcdn.net/thumb/C408x596/?fname=https%3A%2F%2Ft1.daumcdn.net%2Fmovie%2Ff3b63060bb07e3295c1cc737b71c9814b5ca121f"},{"title":"나의 올드 오크","contents":"24.01.17","link":"https://movie.daum.net/moviedb/main?movieId=170312","retrieved":1703304726690,"image":"https://img1.daumcdn.net/thumb/C408x596/?fname=https%3A%2F%2Ft1.daumcdn.net%2Fmovie%2Fd93a10a5bd1ccc9436ee4c21d6245d826c129001"},{"title":"밴디트","contents":"23.12.28","link":"https://movie.daum.net/moviedb/main?movieId=162977","retrieved":1703119558961,"image":"https://img1.daumcdn.net/thumb/C408x596/?fname=https%3A%2F%2Ft1.daumcdn.net%2Fmovie%2Fe6b7bc1a7d33511594b5384bc8afa1194c555b7c"},{"title":"미스 샴푸","contents":"23.12.28","link":"https://movie.daum.net/moviedb/main?movieId=172288","retrieved":1703668214314,"image":"https://img1.daumcdn.net/thumb/C408x596/?fname=https%3A%2F%2Ft1.daumcdn.net%2Fmovie%2F835393d1739f96099b6db2807774902e5af956bd"},{"title":"버려진 사람들","contents":"23.12.31","link":"https://movie.daum.net/moviedb/main?movieId=165796","retrieved":1703668214318,"image":"https://img1.daumcdn.net/thumb/C408x596/?fname=https%3A%2F%2Ft1.daumcdn.net%2Fmovie%2F719566bc570b1be11bd44d4172605fefcaf1d332"},{"title":"시네마틱 노블 2","contents":"23.12","link":"https://movie.daum.net/moviedb/main?movieId=176202","retrieved":1703153474035},{"title":"간신의 피","contents":"24.01.03","link":"https://movie.daum.net/moviedb/main?movieId=174777","retrieved":1703499090188,"image":"https://img1.daumcdn.net/thumb/C408x596/?fname=https%3A%2F%2Ft1.daumcdn.net%2Fmovie%2Fa8600242f22dc443f079741d8b8ba2d99bd5b41f"},{"title":"안데스 설원의 생존자들","contents":"24.01.04","link":"https://movie.daum.net/moviedb/main?movieId=172702","retrieved":1703668214325,"image":"https://img1.daumcdn.net/thumb/C408x596/?fname=https%3A%2F%2Ft1.daumcdn.net%2Fmovie%2F7f7c4d73b8870c754d8d549446aea84e404543d9"},{"title":"사랑의 스잔나","contents":"24.01.04","link":"https://movie.daum.net/moviedb/main?movieId=21314","retrieved":1703560270160,"image":"https://img1.daumcdn.net/thumb/C408x596/?fname=https%3A%2F%2Ft1.daumcdn.net%2Fmovie%2F88d4ffcc80798a878a9d1845353200d1259b2d75"},{"title":"스즈메의 문단속","contents":"24.01.10","link":"https://movie.daum.net/moviedb/main?movieId=161806","retrieved":1703632306264,"image":"https://img1.daumcdn.net/thumb/C408x596/?fname=https%3A%2F%2Ft1.daumcdn.net%2Fmovie%2F3a684ccaeb7aeac8e3f060ffe7249f7fe039443a"},{"title":"노 베어스","contents":"24.01.10","link":"https://movie.daum.net/moviedb/main?movieId=162628","retrieved":1703632306252,"image":"https://img1.daumcdn.net/thumb/C408x596/?fname=https%3A%2F%2Ft1.daumcdn.net%2Fmovie%2Fb7a16675f24ce4d9a5da39ddb1e722e418bf2754"}]}