{"title":"다음 영화 ─ 매거진","url":"https://movie.daum.net/contents/1boon","favicon":"https://movie.daum.net/contents/favicon.ico","elements":[{"title":"어벤져스 떠나고 플래시가 왔다..DC 최고 완성도","contents":"맥스무비","link":"https://v.daum.net/v/1fOv3p9rRr","retrieved":1686278107736,"image":"https://img1.daumcdn.net/thumb/S510x290/?fname=https%3A%2F%2Ft1.daumcdn.net%2Fnews%2F202306%2F09%2Fmaxmovie%2F20230609113358289ghey.jpg"},{"title":"한선화가 결혼했다며 깜짝 공개한 남편 정체","contents":"필더무비","link":"https://v.daum.net/v/fNQIRKQSOr","retrieved":1686278107741,"image":"https://img1.daumcdn.net/thumb/S510x290/?fname=https%3A%2F%2Ft1.daumcdn.net%2Fnews%2F202306%2F09%2Ffeelthemovie%2F20230609113015142eezh.jpg"},{"title":"귀여워서 자세히 봤는데…30년후 톱스타되는 소년들","contents":"필더무비","link":"https://v.daum.net/v/WOLWElXe2P","retrieved":1686272495509,"image":"https://img1.daumcdn.net/thumb/S510x290/?fname=https%3A%2F%2Ft1.daumcdn.net%2Fnews%2F202306%2F09%2Ffeelthemovie%2F20230609093000485vamk.jpg"},{"title":"'토르'에게 가장 큰 비평가라는 인물의 정체는?","contents":"삶은영화","link":"https://v.daum.net/v/bY68t0Kw1e","retrieved":1686278107741,"image":"https://img1.daumcdn.net/thumb/S510x290/?fname=https%3A%2F%2Ft1.daumcdn.net%2Fnews%2F202306%2F09%2FBoiledMovie%2F20230609085943277yhje.png"},{"title":"열여덟, 평범한 두 소녀에게 생긴 일","contents":"맥스무비","link":"https://v.daum.net/v/HWLBjq8Cyt","retrieved":1686265892713,"image":"https://img1.daumcdn.net/thumb/S510x290/?fname=https%3A%2F%2Ft1.daumcdn.net%2Fnews%2F202306%2F09%2Fmaxmovie%2F20230609080052034chse.jpg"},{"title":"무시무시한 '사채업'의 세계에서 두 남자는 과연...","contents":"맥스무비","link":"https://v.daum.net/v/xChXveNFTc","retrieved":1686237082616,"image":"https://img1.daumcdn.net/thumb/S510x290/?fname=https%3A%2F%2Ft1.daumcdn.net%2Fnews%2F202306%2F09%2Fmaxmovie%2F20230609000120012lyjn.jpg"},{"title":"잘생기고 연기도 잘하는데…연출도 잘한다는 톱스타","contents":"필더무비","link":"https://v.daum.net/v/HRUyUlXeDg","retrieved":1686219107033,"image":"https://img1.daumcdn.net/thumb/S510x290/?fname=https%3A%2F%2Ft1.daumcdn.net%2Fnews%2F202306%2F08%2Ffeelthemovie%2F20230608202233922dxrq.png"},{"title":"‘무간도’ 이후 20년만에 580억 대작으로 다시 만난 양조위·유덕화","contents":"삶은영화","link":"https://v.daum.net/v/UjoVQHpaHi","retrieved":1686215483107,"image":"https://img1.daumcdn.net/thumb/S510x290/?fname=https%3A%2F%2Ft1.daumcdn.net%2Fnews%2F202306%2F08%2FBoiledMovie%2F20230608174019702naaf.png"},{"title":"DC '플래시' 개봉 전 뚜껑 열어보니... 마블 눌렀다?","contents":"맥스무비","link":"https://v.daum.net/v/W7QWFcI9lj","retrieved":1686212017112,"image":"https://img1.daumcdn.net/thumb/S510x290/?fname=https%3A%2F%2Ft1.daumcdn.net%2Fnews%2F202306%2F09%2Fmaxmovie%2F20230609112902042vrwv.jpg"},{"title":"오늘 유독 '송해' 선생님이 생각나는 이유는...","contents":"맥스무비","link":"https://v.daum.net/v/ftH24ytnrf","retrieved":1686212017113,"image":"https://img1.daumcdn.net/thumb/S510x290/?fname=https%3A%2F%2Ft1.daumcdn.net%2Fnews%2F202306%2F08%2Fmaxmovie%2F20230608165803417gixh.jpg"},{"title":"현재 전 세계에서 박수 받고 있는 韓신혼부부","contents":"맥스무비","link":"https://v.daum.net/v/uelCSRatYa","retrieved":1686212017115,"image":"https://img1.daumcdn.net/thumb/S510x290/?fname=https%3A%2F%2Ft1.daumcdn.net%2Fnews%2F202306%2F08%2Fmaxmovie%2F20230608165618472qeit.jpg"},{"title":"'톰크루즈'와 함께 한국 오는 역대급 배우들 '소식'","contents":"맥스무비","link":"https://v.daum.net/v/Krk0jq8CSv","retrieved":1686215483113,"image":"https://img1.daumcdn.net/thumb/S510x290/?fname=https%3A%2F%2Ft1.daumcdn.net%2Fnews%2F202306%2F08%2Fmaxmovie%2F20230608163634239iytv.jpg"},{"title":"영화 '반도' 이후 전해진 반가운 소식!","contents":"맥스무비","link":"https://v.daum.net/v/7gYwBIYxnK","retrieved":1686212017116,"image":"https://img1.daumcdn.net/thumb/S510x290/?fname=https%3A%2F%2Ft1.daumcdn.net%2Fnews%2F202306%2F08%2Fmaxmovie%2F20230608163010517bvhi.jpg"},{"title":"'뉴진스' 아버지가 영화제 찾은 놀라운 이유는?","contents":"맥스무비","link":"https://v.daum.net/v/VwtV7mT6Oi","retrieved":1686212017117,"image":"https://img1.daumcdn.net/thumb/S510x290/?fname=https%3A%2F%2Ft1.daumcdn.net%2Fnews%2F202306%2F08%2Fmaxmovie%2F20230608162551480lgdp.jpg"},{"title":"촬영중 너무 잘 성장해서 감독이 굶기려 했던 아역배우","contents":"필더무비","link":"https://v.daum.net/v/fecmoMg1Mo","retrieved":1686204849634,"image":"https://img1.daumcdn.net/thumb/S510x290/?fname=https%3A%2F%2Ft1.daumcdn.net%2Fnews%2F202306%2F08%2Ffeelthemovie%2F20230608151010564lqco.jpg"},{"title":"12년간 연애하고 함께 작품도 출연한 스타 커플,결국…","contents":"필더무비","link":"https://v.daum.net/v/pmwZ7rv8Kj","retrieved":1686201046469,"image":"https://img1.daumcdn.net/thumb/S510x290/?fname=https%3A%2F%2Ft1.daumcdn.net%2Fnews%2F202306%2F08%2Ffeelthemovie%2F20230608133215688aryx.jpg"},{"title":"'앤트맨' 딸 피넛이 이렇게나 자랐다고?","contents":"삶은영화","link":"https://v.daum.net/v/Z18ctgwzKX","retrieved":1686197581315,"image":"https://img1.daumcdn.net/thumb/S510x290/?fname=https%3A%2F%2Ft1.daumcdn.net%2Fnews%2F202306%2F08%2FBoiledMovie%2F20230608131019411smoz.png"},{"title":"커플 연기도 했는데, 결별해 버린 실제 배우 커플","contents":"알려줌 ALZi Media","link":"https://v.daum.net/v/qSElBWFL3r","retrieved":1686197581316,"image":"https://img1.daumcdn.net/thumb/S510x290/?fname=https%3A%2F%2Ft1.daumcdn.net%2Fnews%2F202306%2F08%2Ffanzeel%2F20230608125013363eohq.jpg"},{"title":"너무 예뻐서 톱스타들이 극찬했던 무명 단역 여배우","contents":"필더무비","link":"https://v.daum.net/v/4KKkTsyPML","retrieved":1686194133204,"image":"https://img1.daumcdn.net/thumb/S510x290/?fname=https%3A%2F%2Ft1.daumcdn.net%2Fnews%2F202306%2F08%2Ffeelthemovie%2F20230608113019368lmfy.jpg"},{"title":"예고편 하나 없이 공개한다는 거장의 진짜 마지막 작품","contents":"삶은영화","link":"https://v.daum.net/v/3bYWydj3GH","retrieved":1686191253045,"image":"https://img1.daumcdn.net/thumb/S510x290/?fname=https%3A%2F%2Ft1.daumcdn.net%2Fnews%2F202306%2F08%2FBoiledMovie%2F20230608140558608eiug.png"}]}